Workbook
Name Acessos: #REF!
Name Acessos: #REF!
Name Acessos: #REF!
Name Acessos: #REF!
Name assim: #REF!
Name assim: #REF!
Name assim: #REF!
Name assim: #REF!
Name Barragem: #REF!
Name Barragem: #REF!
Name Barragem: #REF!
Name Barragem: #REF!
Name composicao: #REF!
Name composicao: #REF!
Name Database: #REF!
Name Database: #REF!
Name Database: #REF!
Name Database: #REF!
Name Desp._Complementares: #REF!
Name Desp._Complementares: #REF!
Name Desp._Complementares: #REF!
Name Desp._Complementares: #REF!
Name EFETIVO: #REF!
Name EFETIVO: #REF!
Name EQUIPAMENTO: #REF!
Name EQUIPAMENTO: #REF!
Name EQUIPAMENTO: #REF!
Name EQUIPAMENTO: #REF!
Name INCC: #REF!
Name INCC: #REF!
Name k: #REF!
Name k: #REF!
Name numeração: #REF!+1
Name numeração: #REF!+1
Name Recorder: #REF!
Name Recorder: #REF!
Name Recorder: #REF!
Name Recorder: #REF!
Name SD: #REF!
Name SD: #REF!
Name SD: #REF!
Name SD: #REF!
Name TBP: #REF!
Name TBP: #REF!
Name teste: #REF!*2*9/1.23
Name teste: #REF!*2*9/1.23
Name teste: #REF!*2*9/1.23
Name teste: #REF!*2*9/1.23
Name tfgbfc: #REF!
Name tfgbfc: #REF!
Name Total_Obra: SUM(#REF!,#REF!,#REF!)
Name Total_Obra: SUM(#REF!,#REF!,#REF!)
Name Total_Obra: SUM(#REF!,#REF!,#REF!)
Name Total_Obra: SUM(#REF!,#REF!,#REF!)
Name Tunel: #REF!
Name Tunel: #REF!
Name Tunel: #REF!
Name Tunel: #REF!
Name UN: #REF!
Name UN: #REF!

Sheet PLANILHA
A1: Item | B1: Comp | C1: Insumos | D1: Cód | E1: Descricao | F1: Unid | G1: Arred | H1: Arred | I1: Link | J1: Conferencia
A2: 1 | E2: SERVIÇOS PRELIMINARES
A3: 2 | B3: IS0390 | E3: DEMOLIÇÕES, REMOÇÕES E BOTA-FORA DE DE MATERIAL DEMOLIDO | F3: VB | H3: =ROUND(I3,2) -> 0 | J3: =H3=G3 -> TRUE
A4: 2 | B4: CC1618 | E4: LIMPEZA SUPERFICIAL DO TERRENO | F4: M2 | H4: =ROUND(I4,2) -> 0 | J4: =H4=G4 -> TRUE
A5: 2 | B5: CV0001 | E5: LOCAÇÃO DA OBRA (IMPLANTAÇÃO COM DIMENSÕES MENORES) | F5: M2 | H5: =ROUND(I5,2) -> 0 | J5: =H5=G5 -> TRUE
A6: 2 | B6: CZ0042 | E6: LOCAÇÃO DE OBRAS (IMPLANTAÇÃO COM DIMENSÕES MAIORES) | F6: M2 | H6: =ROUND(I6,2) -> 0 | J6: =H6=G6 -> TRUE
A7: 2 | B7: IS0132 | E7: TOPOGRAFIA | F7: DIA | H7: =ROUND(I7,2) -> 0 | J7: =H7=G7 -> TRUE
A8: 2 | B8: IS4572 | E8: TOPOGRAFIA (MENSAL) | F8: MÊS | H8: =ROUND(I8,2) -> 0 | J8: =H8=G8 -> TRUE
A10: 1 | E10: TERRAPLENAGEM - Estimativa
A11: 2 | B11: IT1050 | E11: MOBILIZAÇÃO/DESMOBILIZAÇÃO DE EQUIPAMENTO DE TERRAPLENAGEM | F11: VB | H11: =ROUND(I11,2) -> 0 | J11: =H11=G11 -> TRUE
A12: 2 | B12: IS4614 | E12: LIMPEZA SUPERFICIAL DO TERRENO (E=0,25CM) | F12: M3 | H12: =ROUND(I12,2) -> 0 | J12: =H12=G12 -> TRUE
A13: 2 | B13: IS0093 | E13: ESCAVAÇÃO EM MATERIAL DE 1ª CATEGORIA, CARGA, TRANSPORTE E BOTA-FORA - Estimado | F13: M3 | H13: =ROUND(I13,2) -> 0 | J13: =H13=G13 -> TRUE
A14: 2 | B14: IS0094 | E14: ESCAVAÇÃO EM MATERIAL DE 1ª CATEGORIA - Estimado | F14: M3 | H14: =ROUND(I14,2) -> 0 | J14: =H14=G14 -> TRUE
A15: 2 | B15: IS0104 | E15: CARGA, TRANSPORTE E BOTA FORA DE MATERIAL EXCEDENTE | F15: M3 | H15: =ROUND(I15,2) -> 0 | J15: =H15=G15 -> TRUE
A16: 2 | B16: IS1671 | E16: ATERRO COMPACTADO - Estimado | F16: M3 | H16: =ROUND(I16,2) -> 0 | J16: =H16=G16 -> TRUE
A17: 2 | B17: IS0092 | E17: EMPRÉSTIMO DE TERRA | F17: M3 | H17: =ROUND(I17,2) -> 0 | J17: =H17=G17 -> TRUE
A19: 1 | E19: CONTENÇÃO
A20: 2 | E20: PAREDE DIAFRAGMA
A21: 3 | E21: MURETA GUIA
A22: 4 | B22: CB0709 | E22: ESCAVAÇÃO MANUAL DE VALAS | F22: M3 | H22: =ROUND(I22,2) -> 0 | J22: =H22=G22 -> TRUE
A23: 4 | B23: CP2007 | E23: FORMA PARA BLOCOS / CINTAS / RESERVATÓRIO | F23: M2 | H23: =ROUND(I23,2) -> 0 | J23: =H23=G23 -> TRUE
A24: 4 | B24: CP2002 | E24: ARMAÇÃO AÇO CA-50A/60B | F24: KG | H24: =ROUND(I24,2) -> 0 | J24: =H24=G24 -> TRUE
A25: 4 | B25: CC1534 | E25: CONCRETO FCK 20,0 MPa LANÇADO EM FUNDAÇÕES | F25: M3 | H25: =ROUND(I25,2) -> 0 | J25: =H25=G25 -> TRUE
A26: 4 | B26: CB0735 | E26: REATERRO COMPACTADO DE VALAS | F26: M3 | H26: =ROUND(I26,2) -> 0 | J26: =H26=G26 -> TRUE
A27: 4 | B27: CN0502 | E27: TRANSPORTE HORIZONTAL E BOTA FORA DE MATERIAL EXCEDENTE (CAÇAMBA) | F27: M3 | H27: =ROUND(I27,2) -> 0 | J27: =H27=G27 -> TRUE
A28: 3 | E28: PAREDES DIAFRAGMA
A29: 4 | B29: IS2814 | E29: EXECUÇÃO DE PAREDE DIAFRAGMA MOLDADA "IN LOCO" ESCAVADA MECANICAMENTE COM O EMPREGO DE LAMA BENTONÍTICA, ATÉ A PROFUNDIDADE DE PROJETO, COMPREENDIDA DE PERFURAÇÃO, FORNECIMENTO DA LAMA BENTONÍTICA, COLOCAÇÃO DA ARMADURA E CONCRETAGEM DA PAREDE - ESP=40CM | F29: M2 | H29: =ROUND(I29,2) -> 0 | J29: =H29=G29 -> TRUE
A30: 4 | B30: CP2002 | E30: ARMAÇÃO AÇO CA-50A/60B | F30: KG | H30: =ROUND(I30,2) -> 0 | J30: =H30=G30 -> TRUE
A31: 4 | B31: CC1559 | E31: CONCRETO ESPECIAL BOMBEADO FCK 20MPa SLUMP 20±2CM | F31: M3 | H31: =ROUND(I31,2) -> 0 | J31: =H31=G31 -> TRUE
A32: 4 | B32: CB0206 | E32: DEMOLIÇÃO DE ESTRUTURA DE CONCRETO DAS LAMELAS DA PAREDE DIAFRAGMA ATÉ A COTA DE ARRASAMENTO E MURETAS GUIAS | F32: M3 | H32: =ROUND(I32,2) -> 0 | J32: =H32=G32 -> TRUE
A33: 4 | B33: IS5713 | E33: REMOÇÃO DE LAMA BENTONÍTICA NÃO-REAPROVEITÁVEL PARA BOTA-FORA AUTORIZADO E LEGALIZADO | F33: M3 | H33: =ROUND(I33,2) -> 0 | J33: =H33=G33 -> TRUE
A34: 4 | B34: CN0502 | E34: TRANSPORTE HORIZONTAL E BOTA FORA DE MATERIAL EXCEDENTE (CAÇAMBA) | F34: M3 | H34: =ROUND(I34,2) -> 0 | J34: =H34=G34 -> TRUE
A35: 3 | E35: VIGAS DE TRAVAMENTO
A36: 4 | B36: CB0709 | E36: ESCAVAÇÃO MANUAL DE VALAS | F36: M3 | H36: =ROUND(I36,2) -> 0 | J36: =H36=G36 -> TRUE
A37: 4 | B37: CP2007 | E37: FORMA PARA BLOCOS / CINTAS / RESERVATÓRIO | F37: M2 | H37: =ROUND(I37,2) -> 0 | J37: =H37=G37 -> TRUE
A38: 4 | B38: CP2002 | E38: ARMAÇÃO AÇO CA-50A/60B | F38: KG | H38: =ROUND(I38,2) -> 0 | J38: =H38=G38 -> TRUE
A39: 4 | B39: CC6048 | E39: CONCRETO FCK 30,0 MPA LANÇADO EM FUNDAÇÕES | F39: M3 | H39: =ROUND(I39,2) -> 0 | J39: =H39=G39 -> TRUE
A40: 4 | B40: CB0735 | E40: REATERRO COMPACTADO DE VALAS | F40: M3 | H40: =ROUND(I40,2) -> 0 | J40: =H40=G40 -> TRUE
A41: 4 | B41: CN0502 | E41: TRANSPORTE HORIZONTAL E BOTA FORA DE MATERIAL EXCEDENTE (CAÇAMBA) | F41: M3 | H41: =ROUND(I41,2) -> 0 | J41: =H41=G41 -> TRUE
A42: 2 | E42: MURO DE ARRIMO
A43: 3 | B43: CB0709 | E43: ESCAVAÇÃO MANUAL DE VALAS | F43: M3 | H43: =ROUND(I43,2) -> 0 | J43: =H43=G43 -> TRUE
A44: 3 | B44: CB4011 | E44: ACERTO E APILOAMENTO DE FUNDO DE VALAS | F44: M2 | H44: =ROUND(I44,2) -> 0 | J44: =H44=G44 -> TRUE
A45: 3 | B45: CC1519 | E45: LASTRO DE CONCRETO FCK 9,0 MPA | F45: M3 | H45: =ROUND(I45,2) -> 0 | J45: =H45=G45 -> TRUE
A46: 3 | B46: CP2007 | E46: FORMA PARA BLOCOS / CINTAS / RESERVATÓRIO | F46: M2 | H46: =ROUND(I46,2) -> 0 | J46: =H46=G46 -> TRUE
A47: 3 | B47: CP2002 | E47: ARMAÇÃO AÇO CA-50A/60B | F47: KG | H47: =ROUND(I47,2) -> 0 | J47: =H47=G47 -> TRUE
A48: 3 | B48: CC6048 | E48: CONCRETO FCK 30,0 MPA LANÇADO EM FUNDAÇÕES | F48: M3 | H48: =ROUND(I48,2) -> 0 | J48: =H48=G48 -> TRUE
A49: 3 | B49: CC1572 | E49: BLOCO DE CONCRETO VAZADO L=15CM PREENCHIDO COM CONCRETO FCK 20,0MPa | F49: M2 | H49: =ROUND(I49,2) -> 0 | J49: =H49=G49 -> TRUE
A50: 3 | B50: CC1573 | E50: BLOCO DE CONCRETO VAZADO L=20CM PREENCHIDO COM CONCRETO FCK 20,0MPa | F50: M2 | H50: =ROUND(I50,2) -> 0 | J50: =H50=G50 -> TRUE
A51: 3 | B51: CB0735 | E51: REATERRO COMPACTADO DE VALAS | F51: M3 | H51: =ROUND(I51,2) -> 0 | J51: =H51=G51 -> TRUE
A52: 3 | B52: CN0502 | E52: TRANSPORTE HORIZONTAL E BOTA FORA DE MATERIAL EXCEDENTE (CAÇAMBA) | F52: M3 | H52: =ROUND(I52,2) -> 0 | J52: =H52=G52 -> TRUE
A53: 2 | E53: CONTRAFORTE
A54: 3 | E54: ESCAVAÇÃO
A55: 4 | B55: IS2172 | E55: ABERTURA MECANIZADA DE NICHO | F55: M3 | H55: =ROUND(I55,2) -> 0 | J55: =H55=G55 -> TRUE
A56: 3 | E56: TUBULÃO
A57: 4 | B57: IT1026 | E57: MOBILIZAÇÃO DE EQUIPAMENTO PARA FUNDAÇÃO TRADO | F57: VB | H57: =ROUND(I57,2) -> 0 | J57: =H57=G57 -> TRUE
A58: 4 | B58: IS0172 | E58: ESCAVAÇÃO DE TUBULÃO (BASE+ RODAPÉ) | F58: M3 | H58: =ROUND(I58,2) -> 0 | J58: =H58=G58 -> TRUE
A59: 4 | B59: CP2002 | E59: ARMAÇÃO AÇO CA-50A/60B | F59: KG | H59: =ROUND(I59,2) -> 0 | J59: =H59=G59 -> TRUE
A60: 4 | B60: CZ1535 | E60: CONCRETO FCK 25,0 MPA LANÇADO EM FUNDAÇÕES | F60: M3 | H60: =ROUND(I60,2) -> 0 | J60: =H60=G60 -> TRUE
A61: 3 | E61: BLOCOS
A62: 4 | B62: CB0709 | E62: ESCAVAÇÃO MANUAL DE VALAS | F62: M3 | H62: =ROUND(I62,2) -> 0 | J62: =H62=G62 -> TRUE
A63: 4 | B63: CB4011 | E63: ACERTO E APILOAMENTO DE FUNDO DE VALAS | F63: M2 | H63: =ROUND(I63,2) -> 0 | J63: =H63=G63 -> TRUE
A64: 4 | B64: CC1519 | E64: LASTRO DE CONCRETO FCK 9,0 MPA | F64: M3 | H64: =ROUND(I64,2) -> 0 | J64: =H64=G64 -> TRUE
A65: 4 | B65: CP2007 | E65: FORMA PARA BLOCOS E CINTAS | F65: M2 | H65: =ROUND(I65,2) -> 0 | J65: =H65=G65 -> TRUE
A66: 4 | B66: CP2002 | E66: ARMAÇÃO AÇO CA-50A/60B | F66: KG | H66: =ROUND(I66,2) -> 0 | J66: =H66=G66 -> TRUE
A67: 4 | B67: CZ1535 | E67: CONCRETO FCK 25,0 MPA LANÇADO EM FUNDAÇÕES | F67: M3 | H67: =ROUND(I67,2) -> 0 | J67: =H67=G67 -> TRUE
A68: 4 | B68: CB0735 | E68: REATERRO COMPACTADO DE VALAS | F68: M3 | H68: =ROUND(I68,2) -> 0 | J68: =H68=G68 -> TRUE
A69: 3 | E69: CONTRAFORTE
A70: 4 | B70: CP2001 | E70: FORMA PARA SUPER-ESTRUTURA | F70: M2 | H70: =ROUND(I70,2) -> 0 | J70: =H70=G70 -> TRUE
A71: 4 | B71: CP2002 | E71: ARMAÇÃO AÇO CA-50A/60B | F71: KG | H71: =ROUND(I71,2) -> 0 | J71: =H71=G71 -> TRUE
A72: 4 | B72: CC1538 | E72: CONCRETO BOMBEADO FCK 25,0 MPa LANÇADO EM ESTRUTURA | F72: M3 | H72: =ROUND(I72,2) -> 0 | J72: =H72=G72 -> TRUE
A73: 3 | E73: FECHAMENTO DE BLOCOS
A74: 4 | B74: CB0709 | E74: ESCAVAÇÃO MANUAL DE VALAS | F74: M3 | H74: =ROUND(I74,2) -> 0 | J74: =H74=G74 -> TRUE
A75: 4 | B75: CC1573 | E75: BLOCO VAZADO L=20CM DE CONCRETO PREENCHIDO COM MASSA | F75: M2 | H75: =ROUND(I75,2) -> 0 | J75: =H75=G75 -> TRUE
A76: 3 | E76: VIGAS DE TRAVAMENTO (INFERIOR / MÉDIA / SUPERIOR)
A77: 4 | B77: CP2001 | E77: FORMA PARA SUPER-ESTRUTURA | F77: M2 | H77: =ROUND(I77,2) -> 0 | J77: =H77=G77 -> TRUE
A78: 4 | B78: CP2002 | E78: ARMAÇÃO AÇO CA-50A/60B | F78: KG | H78: =ROUND(I78,2) -> 0 | J78: =H78=G78 -> TRUE
A79: 4 | B79: CC1538 | E79: CONCRETO BOMBEADO FCK 25,0 MPa LANÇADO EM ESTRUTURA | F79: M3 | H79: =ROUND(I79,2) -> 0 | J79: =H79=G79 -> TRUE
A80: 3 | E80: REATERRO E BOTA-FORA
A81: 4 | B81: CB0735 | E81: REATERRO DOS NICHOS | F81: M3 | H81: =ROUND(I81,2) -> 0 | J81: =H81=G81 -> TRUE
A82: 4 | B82: IS0104 | E82: CARGA, TRANSPORTE E BOTA FORA DE MATERIAL EXCEDENTE | F82: M3 | H82: =ROUND(I82,2) -> 0 | J82: =H82=G82 -> TRUE
A83: 2 | E83: RETANGULÃO
A84: 3 | E84: RETANGULÃO - 60x70CM
A85: 4 | B85: IS1172 | E85: ESCAVAÇÃO DE RETANGULÃO | F85: M3 | H85: =ROUND(I85,2) -> 0 | J85: =H85=G85 -> TRUE
A86: 4 | B86: CP2002 | E86: ARMAÇÃO AÇO CA-50A/60B | F86: KG | H86: =ROUND(I86,2) -> 0 | J86: =H86=G86 -> TRUE
A87: 4 | B87: CZ1535 | E87: CONCRETO FCK 25,0 MPA LANÇADO EM FUNDAÇÕES | F87: M3 | H87: =ROUND(I87,2) -> 0 | J87: =H87=G87 -> TRUE
A88: 3 | E88: FECHAMENTO DE BLOCO E VIGA DE TRAVAMENTO
A89: 4 | B89: CB0709 | E89: ESCAVAÇÃO MANUAL DE VALAS | F89: M3 | H89: =ROUND(I89,2) -> 0 | J89: =H89=G89 -> TRUE
A90: 4 | B90: CC1573 | E90: BLOCO VAZADO L=20CM DE CONCRETO PREENCHIDO COM MASSA | F90: M2 | H90: =ROUND(I90,2) -> 0 | J90: =H90=G90 -> TRUE
A91: 3 | E91: VIGA TRAVAMENTO - 60x30CM
A92: 4 | B92: CP2001 | E92: FORMA PARA SUPER-ESTRUTURA | F92: M2 | H92: =ROUND(I92,2) -> 0 | J92: =H92=G92 -> TRUE
A93: 4 | B93: CP2002 | E93: ARMAÇÃO AÇO CA-50A/60B | F93: KG | H93: =ROUND(I93,2) -> 0 | J93: =H93=G93 -> TRUE
A94: 4 | B94: CC1538 | E94: CONCRETO BOMBEADO FCK 25,0 MPa LANÇADO EM ESTRUTURA | F94: M3 | H94: =ROUND(I94,2) -> 0 | J94: =H94=G94 -> TRUE
A95: 3 | E95: BOTA-FORA
A96: 4 | B96: IS0104 | E96: CARGA, TRANSPORTE E BOTA FORA DE MATERIAL EXCEDENTE | F96: M3 | H96: =ROUND(I96,2) -> 0 | J96: =H96=G96 -> TRUE
A98: 1 | E98: FUNDAÇÃO PROFUNDA
A99: 2 | E99: TRADO MECÂNICO
A100: 3 | B100: IT1026 | E100: MOBILIZAÇÃO DE EQUIPAMENTO PARA FUNDAÇÃO TRADO | F100: VB | H100: =ROUND(I100,2) -> 0 | J100: =H100=G100 -> TRUE
A101: 3 | B101: IS1627 | E101: ESTACA TIPO TRADO MECÂNICO Ø300mm | F101: M | H101: =ROUND(I101,2) -> 0 | J101: =H101=G101 -> TRUE
A102: 3 | B102: IS6602 | E102: ESTACA TIPO TRADO MECÂNICO Ø400mm | F102: M | H102: =ROUND(I102,2) -> 0 | J102: =H102=G102 -> TRUE
A103: 3 | B103: IS6603 | E103: ESTACA TIPO TRADO MECÂNICO Ø500mm | F103: M | H103: =ROUND(I103,2) -> 0 | J103: =H103=G103 -> TRUE
...

Sheet PLANILHAS
A1: Item | B1: Comp | C1: Insumos | D1: Cód link | E1: Descrição | F1: Unid | G1: Arred | H1: Arred | I1: Link | J1: Conferencia
A2: PLANILHA MODELO EMPREITEIRO - REV.01 - PROJETO COMPOR: Nº 10013
A4: 001 | E4: TAXA DE ADMINISTRAÇÃO
A5: 001.001 | B5: CX1701 | C5: IS1000 | E5: TAXA DE ADMINISTRAÇÃO - 10% (CUSTOS DIRETOS + INDIRETOS + PROJETOS) | F5: VB | H5: =ROUND(I5,2) -> 0 | J5: =H5=G5 -> TRUE
A7: 002 | E7: PROJETOS / SERVIÇOS TÉCNICOS
A8: 002.001 | B8: CX1702 | C8: IS0293 | E8: PROJETO ARQUITETÔNICO | F8: VB | H8: =ROUND(I8,2) -> 0 | J8: =H8=G8 -> TRUE
A9: 002.002 | B9: CX1703 | C9: IS1261 | E9: PROJETO DE FACHADA | F9: VB | H9: =ROUND(I9,2) -> 0 | J9: =H9=G9 -> TRUE
A10: 002.003 | B10: CX1704 | C10: IS1262 | E10: PROJETO DE INSTALAÇÕES COMPLEMENTARES | F10: VB | H10: =ROUND(I10,2) -> 0 | J10: =H10=G10 -> TRUE
A11: 002.004 | B11: CX1705 | C11: IS0294 | E11: PROJETO DE INSTALAÇÕES ELÉTRICAS, ESPECIAIS/TELEFONIA, HIDRÁULICO-SANITÁRIAS | F11: VB | H11: =ROUND(I11,2) -> 0 | J11: =H11=G11 -> TRUE
A12: 002.005 | B12: CX1706 | C12: IS1263 | E12: PROJETO DE PISO DE CONCRETO ARMADO E PISO PARA ÁREA EXTERNA | F12: VB | H12: =ROUND(I12,2) -> 0 | J12: =H12=G12 -> TRUE
A13: 002.006 | B13: CX1707 | C13: IS0604 | E13: PROJETO DE PREVENÇÃO E COMBATE A INCÊNDIO | F13: VB | H13: =ROUND(I13,2) -> 0 | J13: =H13=G13 -> TRUE
A14: 002.007 | B14: CX1708 | C14: IS1264 | E14: PROJETO DECORAÇÃO ÁREA COMUM | F14: VB | H14: =ROUND(I14,2) -> 0 | J14: =H14=G14 -> TRUE
A15: 002.008 | B15: CX1709 | C15: IS9758 | E15: PROJETO DETALHAMENTO | F15: VB | H15: =ROUND(I15,2) -> 0 | J15: =H15=G15 -> TRUE
A16: 002.009 | B16: CX1710 | C16: IS1265 | E16: PROJETO ESQUADRIAS | F16: VB | H16: =ROUND(I16,2) -> 0 | J16: =H16=G16 -> TRUE
A17: 002.010 | B17: CX1711 | C17: IS0126 | E17: PROJETO ESTRUTURAL | F17: VB | H17: =ROUND(I17,2) -> 0 | J17: =H17=G17 -> TRUE
A18: 002.011 | B18: CX1712 | C18: IS1261 | E18: PROJETO FACHADA | F18: VB | H18: =ROUND(I18,2) -> 0 | J18: =H18=G18 -> TRUE
A19: 002.012 | B19: CX1713 | C19: IS0295 | E19: PROJETO FUNDAÇÃO | F19: VB | H19: =ROUND(I19,2) -> 0 | J19: =H19=G19 -> TRUE
... A34: 002.027 | B34: CX1728 | C34: IS8543 | E34: SONDAGEM | F34: VB | H34: =ROUND(I34,2) -> 0 | J34: =H34=G34 -> TRUE
A36: 003 | E36: CONSULTORIAS
A37: 003.001 | B37: CX1729 | C37: IS3344 | E37: ORÇAMENTO DA OBRA | F37: VB | H37: =ROUND(I37,2) -> 0 | J37: =H37=G37 -> TRUE
A38: 003.002 | B38: CX1730 | C38: IS1282 | E38: PLANEJAMENTO DA OBRA | F38: VB | H38: =ROUND(I38,2) -> 0 | J38: =H38=G38 -> TRUE
A39: 003.003 | B39: CX1731 | C39: IS3345 | E39: ACOMPANHAMENTO FÍSICO DA OBRA | F39: MÊS | H39: =ROUND(I39,2) -> 0 | J39: =H39=G39 -> TRUE
A40: 003.004 | B40: CX1732 | C40: IS1279 | E40: CONTROLE DOS SOLOS | F40: MÊS | H40: =ROUND(I40,2) -> 0 | J40: =H40=G40 -> TRUE
A41: 003.005 | B41: CX1733 | C41: IS2974 | E41: CONTROLE TECNOLÓGICO - ENSAIO DE ROMPIMENTO - ESTIMATIVA | F41: UN | H41: =ROUND(I41,2) -> 0 | J41: =H41=G41 -> TRUE
A42: 003.006 | B42: CX1734 | C42: IS0347 | E42: VISTORIA INICIAL PARA ACOMPANHAMENTO DE REFLEXOS EM EDIFICAÇÕES VIZINHAS | F42: VB | H42: =ROUND(I42,2) -> 0 | J42: =H42=G42 -> TRUE
A44: 004 | E44: CANTEIRO DE OBRAS
A45: 004.001 | B45: CX1735 | C45: IM0926 | E45: PLACA DE OBRA | F45: VB | H45: =ROUND(I45,2) -> 0 | J45: =H45=G45 -> TRUE
A46: 004.002 | B46: CX1736 | C46: IR0010 | E46: TAPUME DE COMPENSADO | F46: M2 | H46: =ROUND(I46,2) -> 0 | J46: =H46=G46 -> TRUE
A47: 004.003 | B47: CX1737 | C47: IS1269 | E47: MOBILIZAÇÃO DE CONTAINERS | F47: VB | H47: =ROUND(I47,2) -> 0 | J47: =H47=G47 -> TRUE
A48: 004.004 | B48: CX1738 | C48: IE2226 | E48: LOCAÇÃO DE CONTAINER ESCRITÓRIO | F48: MÊS | H48: =ROUND(I48,2) -> 0 | J48: =H48=G48 -> TRUE
A49: 004.005 | B49: CX1739 | C49: IE2503 | E49: LOCAÇÃO DE CONTAINER ALMOXARIFADO | F49: MÊS | H49: =ROUND(I49,2) -> 0 | J49: =H49=G49 -> TRUE
A50: 004.006 | B50: CX1740 | C50: IE2228 | E50: LOCAÇÃO DE CONTAINER VESTIÁRIO | F50: MÊS | H50: =ROUND(I50,2) -> 0 | J50: =H50=G50 -> TRUE
A51: 004.007 | B51: CX1741 | C51: IE2227 | E51: LOCAÇÃO DE CONTAINER SANITÁRIO | F51: MÊS | H51: =ROUND(I51,2) -> 0 | J51: =H51=G51 -> TRUE
A52: 004.008 | B52: CX1742 | C52: IE2504 | E52: LOCAÇÃO DE CONTAINER REFEITÓRIO | F52: MÊS | H52: =ROUND(I52,2) -> 0 | J52: =H52=G52 -> TRUE
A53: 004.009 | B53: CX1743 | C53: IS8515 | E53: INSTALAÇÃO PROVISÓRIA DE ENERGIA ELÉTRICA, ÁGUA E ESGOTO | F53: VB | H53: =ROUND(I53,2) -> 0 | J53: =H53=G53 -> TRUE
A54: 004.010 | B54: CX1744 | C54: IO4619 | E54: BARRACÃO PROVISÓRIO DE OBRA + INSTALAÇÃO PROVISÓRIA DE ENERGIA ELÉTRICA, ÁGUA E ESGOTO | F54: VB | H54: =ROUND(I54,2) -> 0 | J54: =H54=G54 -> TRUE
A55: 004.011 | B55: CX1745 | C55: IS3335 | E55: DESMOBILIZAÇÃO DO CANTEIRO DE OBRAS, PESSOAL E EQUIPAMENTOS | F55: VB | H55: =ROUND(I55,2) -> 0 | J55: =H55=G55 -> TRUE
A56: 004.012 | B56: CX1746 | C56: IE2505 | E56: EQUIPAMENTOS E MÓVEIS DE ESCRITÓRIO | F56: VB | H56: =ROUND(I56,2) -> 0 | J56: =H56=G56 -> TRUE
... A58: 004.014 | B58: CX1748 | C58: IS3334 | E58: MANUTENÇÃO DE CANTEIRO DE OBRAS | F58: MÊS | H58: =ROUND(I58,2) -> 0 | J58: =H58=G58 -> TRUE
A60: 005 | E60: MÃO DE OBRA INDIRETO
A61: 005.001 | E61: EQUIPE INDIRETA PERMANENTE DA OBRA
A62: 005.001.001 | B62: CX1749 | C62: IS5693 | E62: ENGENHEIRO COORDENADOR | F62: MÊS | H62: =ROUND(I62,2) -> 0 | J62: =H62=G62 -> TRUE
A63: 005.001.002 | B63: CX1750 | C63: IS0197 | E63: ENGENHEIRO RESIDENTE | F63: MÊS | H63: =ROUND(I63,2) -> 0 | J63: =H63=G63 -> TRUE
A64: 005.001.003 | B64: CX1751 | C64: IH2026 | E64: TÉCNICO DE SEGURANÇA DO TRABALHO | F64: MÊS | H64: =ROUND(I64,2) -> 0 | J64: =H64=G64 -> TRUE
A65: 005.001.004 | B65: CX1752 | C65: IS0198 | E65: ESTAGIÁRIO DE ENGENHARIA | F65: MÊS | H65: =ROUND(I65,2) -> 0 | J65: =H65=G65 -> TRUE
A66: 005.001.005 | B66: CX1753 | C66: IH2012 | E66: ALMOXARIFE | F66: MÊS | H66: =ROUND(I66,2) -> 0 | J66: =H66=G66 -> TRUE
A67: 005.001.006 | B67: CX1754 | C67: IH1906 | E67: AUXILIAR DE ALMOXARIFE | F67: MÊS | H67: =ROUND(I67,2) -> 0 | J67: =H67=G67 -> TRUE
A68: 005.001.007 | B68: CX1755 | C68: IH3287 | E68: APONTADOR | F68: MÊS | H68: =ROUND(I68,2) -> 0 | J68: =H68=G68 -> TRUE
A69: 005.001.008 | B69: CX1756 | C69: IH2011 | E69: MESTRE DE OBRA | F69: MÊS | H69: =ROUND(I69,2) -> 0 | J69: =H69=G69 -> TRUE
A70: 005.001.009 | B70: CX1757 | C70: IH2042 | E70: ENCARREGADO GERAL | F70: MÊS | H70: =ROUND(I70,2) -> 0 | J70: =H70=G70 -> TRUE
A71: 005.001.010 | B71: CX1758 | C71: IH2045 | E71: ENCARREGADO DE FACHADA | F71: MÊS | H71: =ROUND(I71,2) -> 0 | J71: =H71=G71 -> TRUE
A72: 005.001.011 | B72: CX1759 | C72: IH2046 | E72: ENCARREGADO DE SERVENTE | F72: MÊS | H72: =ROUND(I72,2) -> 0 | J72: =H72=G72 -> TRUE
A73: 005.001.012 | B73: CX1760 | C73: IH2023 | E73: ENCARREGADO DE ACABAMENTO | F73: MÊS | H73: =ROUND(I73,2) -> 0 | J73: =H73=G73 -> TRUE
... A90: 005.001.029 | B90: CX1777 | C90: IH2041 | E90: PORTEIRO | F90: MÊS | H90: =ROUND(I90,2) -> 0 | J90: =H90=G90 -> TRUE
A91: 005.002 | E91: ENCARGOS TRABALHISTAS
A92: 005.002.001 | B92: CX1778 | C92: IS4511 | E92: ENCARGOS TRABALHISTAS | F92: VB | H92: =ROUND(I92,2) -> 0 | J92: =H92=G92 -> TRUE
A93: 005.003 | E93: DESPESAS ADICIONAIS
A94: 005.003.001 | B94: CX1779 | C94: IS3336 | E94: CESTA BÁSICA (47 homens) | F94: UN | H94: =ROUND(I94,2) -> 0 | J94: =H94=G94 -> TRUE
A95: 005.003.002 | B95: CX1780 | C95: IS3338 | E95: VALE TRANSPORTE (47 homens) - 4UN/DIA | F95: UN | H95: =ROUND(I95,2) -> 0 | J95: =H95=G95 -> TRUE
A96: 005.003.003 | B96: CX1781 | C96: IS3339 | E96: CAFÉ DA MANHÃ (47 homens) | F96: UN | H96: =ROUND(I96,2) -> 0 | J96: =H96=G96 -> TRUE
A97: 005.003.004 | B97: CX1782 | C97: IS3356 | E97: E.P.I. (47 homens) | F97: MÊS | H97: =ROUND(I97,2) -> 0 | J97: =H97=G97 -> TRUE
A98: 005.003.005 | B98: CX1783 | C98: IS1270 | E98: SECONCI (47 homens) | F98: VB | H98: =ROUND(I98,2) -> 0 | J98: =H98=G98 -> TRUE
A99: 005.003.006 | B99: CX1784 | C99: IS3357 | E99: PCMSO / PCMAT | F99: VB | H99: =ROUND(I99,2) -> 0 | J99: =H99=G99 -> TRUE
A100: 005.004 | E100: DIVERSOS
A101: 005.004.001 | B101: CX1785 | C101: IS3360 | E101: BONIFICAÇÃO MENSAL | F101: MÊS | H101: =ROUND(I101,2) -> 0 | J101: =H101=G101 -> TRUE
A102: 005.004.002 | B102: CX1786 | C102: IS1001 | E102: CUSTO PARA EMISSÃO DE NF EM NOME DA CONSTRUTORA - XX% | F102: MÊS | H102: =ROUND(I102,2) -> 0 | J102: =H102=G102 -> TRUE
A103: 005.005 | E103: SEGURANÇA DO TRABALHO
A104: 005.005.001 | B104: CX1787 | C104: IS1288 | E104: EMPRESA DE SEGURANÇA DO TRABALHO | F104: MÊS | H104: =ROUND(I104,2) -> 0 | J104: =H104=G104 -> TRUE
A106: 006 | E106: EQUIPAMENTOS E FERRAMENTAS
A107: 006.001 | E107: EQUIPAMENTOS
A108: 006.001.001 | B108: CX1788 | C108: IO0257 | E108: BEBEDOURO (compra) | F108: UN | H108: =ROUND(I108,2) -> 0 | J108: =H108=G108 -> TRUE
A109: 006.001.002 | B109: CX1789 | C109: IE2250 | E109: ESTUFA ELÉTRICA (compra) | F109: UN | H109: =ROUND(I109,2) -> 0 | J109: =H109=G109 -> TRUE
A110: 006.001.003 | B110: CX1790 | C110: IE2363 | E110: RÁDIO DE COMUNICAÇÃO MOTOROLA EP150 (compra) | F110: UN | H110: =ROUND(I110,2) -> 0 | J110: =H110=G110 -> TRUE
A111: 006.001.004 | B111: CX1791 | C111: IE0005 | E111: RELÓGIO DE PONTO DIGITAL (compra) | F111: UN | H111: =ROUND(I111,2) -> 0 | J111: =H111=G111 -> TRUE
A112: 006.001.005 | B112: CX1792 | C112: IE2257 | E112: BETONEIRA 400 LITROS SEM CARREGADOR | F112: MÊS | H112: =ROUND(I112,2) -> 0 | J112: =H112=G112 -> TRUE
A113: 006.001.006 | B113: CX1793 | C113: IE6921 | E113: BETONEIRA 580 LITROS COM CARREGADOR | F113: MÊS | H113: =ROUND(I113,2) -> 0 | J113: =H113=G113 -> TRUE
A114: 006.001.007 | B114: CX1794 | C114: IE9315 | E114: BETONEIRA 600 LITROS COM CARREGADOR | F114: MÊS | H114: =ROUND(I114,2) -> 0 | J114: =H114=G114 -> TRUE
A115: 006.001.008 | B115: CX1795 | C115: IE2258 | E115: MOTOR VIBRADOR + MANGOTE | F115: MÊS | H115: =ROUND(I115,2) -> 0 | J115: =H115=G115 -> TRUE
A116: 006.001.009 | B116: CX1796 | C116: IE2254 | E116: SERRA CIRCULAR ELÉTRICA MANUAL | F116: MÊS | H116: =ROUND(I116,2) -> 0 | J116: =H116=G116 -> TRUE
A117: 006.001.010 | B117: CX1797 | C117: IE2229 | E117: SERRA CIRCULAR ELÉTRICA BANCADA | F117: MÊS | H117: =ROUND(I117,2) -> 0 | J117: =H117=G117 -> TRUE
A118: 006.001.011 | B118: CX1798 | C118: IE2263 | E118: COMPACTADOR CM20 TIPO SAPO MECÂNICO | F118: MÊS | H118: =ROUND(I118,2) -> 0 | J118: =H118=G118 -> TRUE
A119: 006.001.012 | B119: CX1799 | C119: IE2255 | E119: MÁQUINA DE CORTAR FERRO - policorte | F119: MÊS | H119: =ROUND(I119,2) -> 0 | J119: =H119=G119 -> TRUE
... A131: 006.001.024 | B131: CX1811 | C131: IE1902 | E131: ELEVADOR TIPO CREMALHEIRA CABINE DUPLA | F131: MÊS | H131: =ROUND(I131,2) -> 0 | J131: =H131=G131 -> TRUE
A132: 006.001.025 | B132: CT2205 | E132: MONTAGEM E DESMONTAGEM DE ELEVADOR CREMALHEIRA | F132: VB | H132: =ROUND(I132,2) -> 0 | J132: =H132=G132 -> TRUE
A133: 006.001.026 | B133: CX1812 | C133: IE2265 | E133: ACESSÓRIOS PARA MONTAGEM DOS ELEVADORES DE OBRA - Lista de materiais fornecida pela Mecan | F133: VB | H133: =ROUND(I133,2) -> 0 | J133: =H133=G133 -> TRUE
A134: 006.001.027 | B134: CX1813 | C134: IE1902 | E134: ELEVADOR TIPO CREMALHEIRA CABINE DUPLA | F134: MÊS | H134: =ROUND(I134,2) -> 0 | J134: =H134=G134 -> TRUE
A135: 006.001.028 | B135: CZ2201 | E135: MONTAGEM E DESMONTAGEM DE ELEVADOR CREMALHEIRA | F135: VB | H135: =ROUND(I135,2) -> 0 | J135: =H135=G135 -> TRUE
A136: 006.001.029 | B136: CX1814 | C136: IE0016 | E136: LOCAÇÃO DE CAMINHÃO MUNCK PARA CARGA/DESCARGA DE ELEVADOR DE CREMALHEIRA | F136: H | H136: =ROUND(I136,2) -> 0 | J136: =H136=G136 -> TRUE
A137: 006.001.030 | B137: CX1815 | C137: IE6000 | E137: FERRAMENTAS LEVES E DISCOS DE CORTE | F137: MÊS | H137: =ROUND(I137,2) -> 0 | J137: =H137=G137 -> TRUE
A138: 006.001.031 | B138: CX1816 | C138: IE0301 | E138: COMPRESSOR 250CPM | F138: MÊS | H138: =ROUND(I138,2) -> 0 | J138: =H138=G138 -> TRUE
A139: 006.001.032 | B139: CT2210 | C139: IE3007 | E139: GRUA | F139: VB | H139: =ROUND(I139,2) -> 0 | J139: =H139=G139 -> TRUE
A140: 006.001.033 | B140: CX1817 | C140: IE3009 | E140: GUINDASTE | F140: DIA | H140: =ROUND(I140,2) -> 0 | J140: =H140=G140 -> TRUE
A141: 006.001.034 | B141: CX1818 | C141: IE3005 | E141: MINIESCAVADEIRA | F141: MÊS | H141: =ROUND(I141,2) -> 0 | J141: =H141=G141 -> TRUE
A142: 006.001.035 | B142: CX1819 | C142: IE3011 | E142: MINI-GRUA | F142: MÊS | H142: =ROUND(I142,2) -> 0 | J142: =H142=G142 -> TRUE
A143: 006.001.036 | B143: CX1820 | C143: IE3004 | E143: RETROESCAVADEIRA | F143: MÊS | H143: =ROUND(I143,2) -> 0 | J143: =H143=G143 -> TRUE
A144: 006.001.037 | B144: CX1821 | C144: IE6001 | E144: MANUTENÇÃO DE EQUIPAMENTOS | F144: MÊS | H144: =ROUND(I144,2) -> 0 | J144: =H144=G144 -> TRUE
A145: 006.002 | E145: ANDAIMES
A146: 006.002.001 | B146: CT1001 | C146: IE1904 | E146: LOCAÇÃO DE ANDAIME LEVE SUSPENSO | F146: MÊS | H146: =ROUND(I146,2) -> 0 | J146: =H146=G146 -> TRUE
A147: 006.002.002 | B147: CT2206 | E147: MONTAGEM E DESMONTAGEM DE ANDAIME LEVE SUSPENSO | F147: UN | H147: =ROUND(I147,2) -> 0 | J147: =H147=G147 -> TRUE
A148: 006.002.003 | B148: CT5001 | C148: IE2373 | E148: LOCAÇÃO DE ANDAIME FACHADEIRO - 422,96 m² | F148: MÊS | H148: =ROUND(I148,2) -> 0 | J148: =H148=G148 -> TRUE
...

Sheet IS GESTOR
A1: Código | B1: Descrição | C1: Unid.
A2: IE0002 | B2: LOCAÇÃO DE CAMISA METÁLICA PARA TUBULÃO | C2: CX
A3: IE0004 | B3: LOCAÇÃO DE VAN | C3: MÊS
A4: IE0005 | B4: RELÓGIO DE PONTO DIGITAL (compra) | C4: UN | D4: Insumo existente no projeto 10013
A5: IE0006 | B5: LOCAÇÃO DIVERSOS MÁQUINAS E EQUIPAMENTOS | C5: MÊS
A6: IE0007 | B6: MINI ESCAVADEIRA | C6: VB
A7: IE0008 | B7: LOCAÇÃO TRADO MECÂNICO | C7: DIA
A8: IE0009 | B8: CAMINHÃO PIPA - estimado | C8: UN
A9: IE0010 | B9: CAMINHÃO PIPA | C9: VIAGE
A10: IE0011 | B10: MONTAGEM E DESMONTAGEM DE ANDAIME FACHADEIRO | C10: M2 | D10: Insumo existente no projeto 10013
A11: IE0012 | B11: MINI GRUA - CAPACIDADE ATÉ 500 KG - MANUTENÇÃO E | C11: MÊS
A12: IE0013 | B12: MINI GRUA - MONTAGEM E DESMONTAGEM | C12: UN
A13: IE0014 | B13: MINI GRUA - ASCENSÃO | C13: UN
A14: IE0015 | B14: MINI GRUA - CAPACIDADE ATÉ 500 KG - LOCAÇÃO | C14: MÊS
A15: IE0016 | B15: LOCAÇÃO DE CAMINHÃO MUNCK PARA CARGA/DESCARGA DE | C15: H | D15: Insumo existente no projeto 10013
A16: IE0023 | B16: ANDAIME TUBULAR PARA SERVIÇOS GERAIS COMPLETO - | C16: M2/ME
A17: IE0024 | B17: ROLO COMPACTADOR | C17: MES
A18: IE0103 | B18: ANDAIME FACHADEIRO COM PISO METALICO | C18: M3
A19: IE0203 | B19: BETONEIRA | C19: H
A20: IE0301 | B20: COMPRESSOR 250CPM | C20: MES | D20: Insumo existente no projeto 10013
A21: IE0303 | B21: COMPACTADOR TIPO PLACA | C21: H
A22: IE0315 | B22: BOMBAS PARA DRENAGEM DE ÁGUA PLUVIAL | C22: MÊS
A23: IE0317 | B23: LAVADORA DE ALTA PRESSÃO WAP | C23: MÊS
A24: IE0318 | B24: LIXADEIRA REF.: ANTARES - Compra | C24: UN
A25: IE0319 | B25: MARTELETE SDS 2KG | C25: MÊS
A26: IE0320 | B26: MARTELO ROMPEDOR 10KG | C26: MES
A27: IE0321 | B27: FURADEIRA BATEDEIRA | C27: MÊS
A28: IE0322 | B28: ESCAVADEIRA | C28: H
A29: IE0324 | B29: MINI-CARREGADEIRA BOBCAT | C29: MÊS
A30: IE0326 | B30: LOCAÇÃO DE ANDAIMES PARA APOIO AOS SERVIÇOS DE | C30: MÊS
A31: IE1030 | B31: MARTELETE 10KG (02 EQUIPAMENTOS / MÊS) | C31: MES
A32: IE1204 | B32: LOCAÇÃO DE GUINDASTE PARA IÇAMENTO DAS ÁRVORES | C32: VB
... A34: IE1312 | B34: PISTOLA HILT / WALSIVA - Finca pino - Compra | C34: UN
A35: IE1313 | B35: GUINCHO COLUNA + CABO | C35: MES | D35: Insumo existente no projeto 10013
A36: IE1314 | B36: ANDAIME PARA SERVIÇOS GERAIS - Estimado | C36: M2
A37: IE1608 | B37: LOCAÇÃO DE BANHEIRO QUÍMICO | C37: MÊS
A38: IE1801 | B38: LOCAÇÃO DE RETRO-ESCAVADEIRA | C38: DIA
A39: IE1902 | B39: ELEVADOR TIPO CREMALHEIRA CABINE DUPLA | C39: MES | D39: Insumo existente no projeto 10013
A40: IE1903 | B40: ELEVADOR TIPO CREMALHEIRA - ASCENSÃO | C40: UN
A41: IE1904 | B41: PLATAFORMA SUPER DE ELEVAÇÃO MANUAL DE 1 A 6 METROS - | C41: MES | D41: Insumo existente no projeto 10013
A42: IE1906 | B42: ESCAVADEIRA | C42: MÊS
A43: IE1907 | B43: ASSISTENTE DE ENGENHARIA - PJ | C43: MÊS
A44: IE2226 | B44: LOCAÇÃO DE CONTAINER ESCRITÓRIO | C44: MES | D44: Insumo existente no projeto 10013
A45: IE2227 | B45: LOCAÇÃO DE CONTAINER SANITÁRIO | C45: MES | D45: Insumo existente no projeto 10013
A46: IE2228 | B46: LOCAÇÃO DE CONTAINER VESTIÁRIO | C46: MÊS | D46: Insumo existente no projeto 10013
A47: IE2229 | B47: SERRA CIRCULAR DE BANCADA | C47: MES | D47: Insumo existente no projeto 10013
A48: IE2233 | B48: MÁQUINA DE CORTAR PAREDE | C48: MÊS
A49: IE2235 | B49: BOB CAT | C49: MES
A50: IE2247 | B50: ESCORAMENTO METÁLICO | C50: M3
A51: IE2248 | B51: CAÇAMBA P/ REMOÇÃO DE ENTULHO | C51: M3 | D51: Insumo existente no projeto 10013
A52: IE2250 | B52: ESTUFA ELÉTRICA (compra) | C52: UN | D52: Insumo existente no projeto 10013
A53: IE2254 | B53: SERRA CIRCULAR ELÉTRICA MANUAL | C53: MES | D53: Insumo existente no projeto 10013
A54: IE2255 | B54: MÁQUINA DE CORTAR FERRO - policorte | C54: MES | D54: Insumo existente no projeto 10013
A55: IE2256 | B55: LIXADEIRA PORTÁTIL | C55: MES | D55: Insumo existente no projeto 10013
A56: IE2257 | B56: BETONEIRA 400 LITROS SEM CARREGADOR | C56: MES | D56: Insumo existente no projeto 10013
A57: IE2258 | B57: MOTOR VIBRADOR + MANGOTE | C57: MES | D57: Insumo existente no projeto 10013
A58: IE2259 | B58: BETONEIRA 420 LITROS COM CARREGADOR | C58: MÊS
A59: IE2260 | B59: SERRA MÁRMORE - makita | C59: MES | D59: Insumo existente no projeto 10013
A60: IE2261 | B60: FURADEIRA BATEDEIRA | C60: MES | D60: Insumo existente no projeto 10013
A61: IE2262 | B61: MARTELETE ROMPEDOR 15KG | C61: MES | D61: Insumo existente no projeto 10013
A62: IE2263 | B62: COMPACTADOR CM20 TIPO SAPO MECÂNICO | C62: MES | D62: Insumo existente no projeto 10013
A63: IE2264 | B63: PISTOLA HILT | C63: MES | D63: Insumo existente no projeto 10013
A64: IE2265 | B64: ACESSÓRIOS PARA MONTAGEM DOS ELEVADORES DE OBRA - | C64: VB | D64: Insumo existente no projeto 10013
A65: IE2266 | B65: RETRO COM PICÃO | C65: MÊS
A66: IE2267 | B66: MANUTENÇÃO PREVENTIVA ELEVADOR CREMALHEIRA | C66: VB | D66: Insumo existente no projeto 10013
A67: IE2268 | B67: FRESADORA | C67: MÊS
A68: IE2269 | B68: MANUTENÇÃO PREVENTIVA ELEVADOR CREMALHEIRA | C68: VB
A69: IE2271 | B69: MÃO FRANCESA PARA BANDEJA SALVA-VIDAS L=2,5M | C69: UN/ME | D69: Insumo existente no projeto 10013
A70: IE2292 | B70: ANDAIME INTERNO - Estimado | C70: M2 | D70: Insumo existente no projeto 10013
A71: IE2305 | B71: FURADEIRA BOSCH SDS (compra) | C71: UN | D71: Insumo existente no projeto 10013
A72: IE2345 | B72: MARTELO DEMOLIDOR 5KG | C72: MÊS
A73: IE2356 | B73: CAÇAMBA P/REMOÇÃO DE ENTULHOS (5M³) | C73: VIAG. | D73: Insumo existente no projeto 10013
A74: IE2357 | B74: MINI GRUA | C74: MÊS
A75: IE2358 | B75: EQUIPAMENTO INFORMATICA (COMPUTADOR) | C75: UN
A76: IE2362 | B76: ANDAIME INTERNO COM PISO E RODAPÉ | C76: M2
A77: IE2363 | B77: RÁDIO DE COMUNICAÇÃO | C77: UN | D77: Insumo existente no projeto 10013
A78: IE2364 | B78: FERRAMENTAS EM GERAL | C78: UN
A79: IE2365 | B79: PONTEIRO ROMPEDOR SDS | C79: MÊS
A80: IE2367 | B80: PLATAFORMA ELEVATÓRIA (3 PLATAFORMAS) | C80: MES
A81: IE2370 | B81: LOCAÇÃO DE BANHEIRO QUÍMICO, INCLUSO 2 MANUTENÇÕES | C81: MÊS
A82: IE2371 | B82: RELÓGIO DE PONTO | C82: MES
A83: IE2372 | B83: MAKITÃO | C83: MES | D83: Insumo existente no projeto 10013
A84: IE2373 | B84: ANDAIME FACHADEIRO SEM PISO METALICO | C84: M2/ME | D84: Insumo existente no projeto 10013
A85: IE2374 | B85: ANDAIME FACHADEIRO | C85: VB
A86: IE2375 | B86: FURADEIRA DE IMPACTO | C86: MES | D86: Insumo existente no projeto 10013
A87: IE2378 | B87: IMPRESSORA - Compra | C87: UN
A88: IE2501 | B88: LOCAÇÃO DE COMPRESSOR PARA TIRANTES | C88: VB
A89: IE2503 | B89: LOCAÇÃO DE CONTAINER ALMOXARIFADO | C89: MES | D89: Insumo existente no projeto 10013
A90: IE2504 | B90: LOCAÇÃO DE CONTAINER REFEITÓRIO | C90: MÊS | D90: Insumo existente no projeto 10013
A91: IE2505 | B91: EQUIPAMENTOS E MÓVEIS DE ESCRITÓRIO | C91: VB | D91: Insumo existente no projeto 10013
A92: IE2587 | B92: BOMBA MANGOTE 3'' | C92: UN
A93: IE2985 | B93: EQUIPAMENTOS - CUSTOS APROPRIADOS | C93: VB
A94: IE2987 | B94: CAÇAMBA P/REMOÇÃO DE ENTULHOS | C94: VIAG.
A95: IE3003 | B95: CAMINHÃO MUNK | C95: DIA
A96: IE3004 | B96: RETROESCAVADEIRA | C96: MES | D96: Insumo existente no projeto 10013
A97: IE3005 | B97: MINIESCAVADEIRA | C97: MES | D97: Insumo existente no projeto 10013
A98: IE3006 | B98: ESMERILHADEIRA | C98: MES | D98: Insumo existente no projeto 10013
A99: IE3007 | B99: GRUA | C99: MES | D99: Insumo existente no projeto 10013
A100: IE3008 | B100: MARTELO | C100: MES | D100: Insumo existente no projeto 10013
A101: IE3009 | B101: GUINDASTE | C101: DIA | D101: Insumo existente no projeto 10013
...

Sheet Lev. padrão
B1: Item | C1: Comp | E1: Descrição | F1: Unid | G1: Total | H1: Quant. | I1: Comp. (m) | J1: Larg. (m) | K1: Altura (m) | L1: Área | M1: Perímetro | N1: DESCONTO / ACRESCIMO
B2: 1 | E2: REVESTIMENTO INTERNO, IMPERMEABILIZAÇÃO, LOUÇAS E METAIS
B3: 1 | E3: PREDIO DE APOIO
B4: 2 | E4: PAVIMENTO TÉRREO
B5: 3 | C5: CP5000 | D5: PB1 | E5: area total de piso | F5: M2
B6: 2 | E6: AREA COMUM | S6: PORTAS | U6: JANELAS
B7: 3 | E7: ÁREA SECA | R7: DESC PAR | S7: DESC ROD | T7: SOLEIRA | U7: PEITORIL
B8: 4 | E8: NOME DO CÔMODO | G8: =SUM(G10:G17) -> 0 | P8: PEÇA | Q8: QUANT | R8: =SUM(R9:R17) -> 0 | S8: =SUM(S9:S17) -> 0 | T8: =SUM(T9:T17) -> 0 | U8: =SUM(U9:U17) -> 0
E9: DADOS PRIMARIOS | P9: j01 | Q9: 1 | R9: =IFERROR(VLOOKUP(P9,'RESUMO_ESQ.'!$A$8:$R$141,6,)*Q9,"") | U9: =IFERROR(VLOOKUP(P9,'RESUMO_ESQ.'!$A$8:$R$141,2,)*Q9,"")
B10: 5 | C10: CP5000 | D10: PB1 | E10: =VLOOKUP(D10,'RESUMO_REV.'!$A$6:$B$94,2,FALSE) -> Camada de regularização / contrapiso e=3,0cm | F10: M2 | G10: =H9*L9 -> 0 | P10: P01 | Q10: 1 | R10: =IFERROR(VLOOKUP(P10,'RESUMO_ESQ.'!$A$8:$R$141,6,)*Q10,"") | S10: =IFERROR(VLOOKUP(P10,'RESUMO_ESQ.'!$A$8:$R$141,2,)*Q10,"") | T10: =IFERROR(VLOOKUP(P10,'RESUMO_ESQ.'!$A$8:$R$141,2,)*Q10,"")
B11: 5 | C11: CS1594 | D11: RB1 | E11: =VLOOKUP(D11,'RESUMO_REV.'!$A$6:$B$94,2,FALSE) -> Chapisco interno | F11: M2 | G11: =H9*(K9*M9-N11) -> 0 | N11: =R8 -> 0 | P11: j01 | Q11: 1 | R11: =IFERROR(VLOOKUP(P11,'RESUMO_ESQ.'!$A$8:$R$141,6,)*Q11,"") | U11: =IFERROR(VLOOKUP(P11,'RESUMO_ESQ.'!$A$8:$R$141,2,)*Q11,"")
B12: 5 | C12: CS1594 | D12: RB3 | E12: =VLOOKUP(D12,'RESUMO_REV.'!$A$6:$B$94,2,FALSE) -> Reboco interno + ponto de masssa | F12: M2 | G12: =H9*(K9*M9-N12) -> 0 | N12: =R8 -> 0
B13: 5 | D13: R1 | E13: =VLOOKUP(D13,'RESUMO_REV.'!$A$6:$B$94,2,FALSE) -> REVESTIMENTO | F13: M2 | G13: =H9*(K9*M13-N13) -> 0 | N13: =R8 -> 0
B14: 5 | D14: P1 | E14: =VLOOKUP(D14,'RESUMO_REV.'!$A$6:$B$94,2,FALSE) -> PISO | F14: M2 | G14: =H9*L9 -> 0
B15: 5 | D15: RP1 | E15: =VLOOKUP(D15,'RESUMO_REV.'!$A$6:$B$94,2,FALSE) -> RODAPÉ | F15: M | G15: =H9*(M9-N15) -> 0 | N15: =S8 -> 0
B16: 5 | D16: S1 | E16: =VLOOKUP(D16,'RESUMO_REV.'!$A$6:$B$94,2,FALSE) -> SOLEIRA | F16: M | G16: =H9*N16 -> 0 | N16: =T8 -> 0
B17: 5 | D17: PT1 | E17: =VLOOKUP(D17,'RESUMO_REV.'!$A$6:$B$94,2,FALSE) -> PEITORIL | F17: M | G17: =H9*N17 -> 0 | N17: =U8 -> 0
B18: 5 | D18: T1 | E18: =VLOOKUP(D18,'RESUMO_REV.'!$A$6:$B$94,2,FALSE) -> TETO | F18: M2 | G18: =+H9*L9 -> 0
B20: 3 | E20: ÁREA MOLHADA
B21: 4 | E21: NOME DO CÔMODO | G21: =SUM(G23:G39) -> 0 | P21: PEÇA | Q21: QUANT | R21: =SUM(R22:R31) -> 0 | S21: =SUM(S22:S31) -> 0 | T21: =SUM(T22:T31) -> 0 | U21: =SUM(U22:U31) -> 0
E22: DADOS PRIMARIOS | P22: j01 | Q22: 1 | R22: =IFERROR(VLOOKUP(P22,'RESUMO_ESQ.'!$A$8:$R$141,6,)*Q22,"") | U22: =IFERROR(VLOOKUP(P22,'RESUMO_ESQ.'!$A$8:$R$141,2,)*Q22,"")
B23: 5 | C23: CP5000 | D23: PB1 | E23: =VLOOKUP(D23,'RESUMO_REV.'!$A$6:$B$94,2,FALSE) -> Camada de regularização / contrapiso e=3,0cm | F23: M2 | G23: =H22*L22 -> 0 | P23: P01 | Q23: 1 | R23: =IFERROR(VLOOKUP(P23,'RESUMO_ESQ.'!$A$8:$R$141,6,)*Q23,"") | S23: =IFERROR(VLOOKUP(P23,'RESUMO_ESQ.'!$A$8:$R$141,2,)*Q23,"") | T23: =IFERROR(VLOOKUP(P23,'RESUMO_ESQ.'!$A$8:$R$141,2,)*Q23,"")
B24: 5 | C24: CS1594 | D24: RB1 | E24: =VLOOKUP(D24,'RESUMO_REV.'!$A$6:$B$94,2,FALSE) -> Chapisco interno | F24: M2 | G24: =H22*(K22*M22-N24) -> 0 | N24: =R21 -> 0 | P24: j01 | Q24: 1 | R24: =IFERROR(VLOOKUP(P24,'RESUMO_ESQ.'!$A$8:$R$141,6,)*Q24,"") | U24: =IFERROR(VLOOKUP(P24,'RESUMO_ESQ.'!$A$8:$R$141,2,)*Q24,"")
B25: 5 | C25: CS1594 | D25: RB2 | E25: =VLOOKUP(D25,'RESUMO_REV.'!$A$6:$B$94,2,FALSE) -> Emboço interno + ponto de masssa | F25: M2 | G25: =H22*(K22*M22-N25) -> 0 | N25: =R21 -> 0
B26: 5 | D26: I1 | E26: =VLOOKUP(D26,IMPER!$A$9:$E$14,2,FALSE) -> IMPERMEABILIZAÇÃO DE LAJE PLANA COM MANTA ASFÁLTICA 4 MM INCLUSIVE PROTEÇÃO MECÂNICA | F26: M2 | G26: =H22*(L22+M22*0.3) -> 0
B27: 5 | D27: R1 | E27: =VLOOKUP(D27,'RESUMO_REV.'!$A$6:$B$94,2,FALSE) -> REVESTIMENTO | F27: M2 | G27: =H22*(K22*M22-N27) -> 0 | N27: =R21 -> 0
B28: 5 | D28: P1 | E28: =VLOOKUP(D28,'RESUMO_REV.'!$A$6:$B$94,2,FALSE) -> PISO | F28: M2 | G28: =H22*L22 -> 0
B29: 5 | D29: RP1 | E29: =VLOOKUP(D29,'RESUMO_REV.'!$A$6:$B$94,2,FALSE) -> RODAPÉ | F29: M | G29: =H22*(M22-N29) -> 0 | N29: =S21 -> 0
B30: 5 | D30: S1 | E30: =VLOOKUP(D30,'RESUMO_REV.'!$A$6:$B$94,2,FALSE) -> SOLEIRA | F30: M | G30: =H22*N30 -> 0 | N30: =T21 -> 0
B31: 5 | D31: PT1 | E31: =VLOOKUP(D31,'RESUMO_REV.'!$A$6:$B$94,2,FALSE) -> PEITORIL | F31: M | G31: =H22*N31 -> 0 | N31: =U21 -> 0
B32: 5 | D32: T1 | E32: =VLOOKUP(D32,'RESUMO_REV.'!$A$6:$B$94,2,FALSE) -> TETO | F32: M2 | G32: =+H22*L22 -> 0
B33: 5 | D33: B1 | E33: =VLOOKUP(D33,'RESUMO_LÇ.MET.'!$A$8:$B$111,2,FALSE) -> BANCADA | F33: M2 | G33: =H22*L33 -> 0
B34: 5 | D34: RB1 | E34: =VLOOKUP(D34,'RESUMO_LÇ.MET.'!$A$8:$B$111,2,FALSE) -> RODABANCA | F34: M | G34: =H22*I34 -> 0
B35: 5 | D35: TT1 | E35: =VLOOKUP(D35,'RESUMO_LÇ.MET.'!$A$8:$B$111,2,FALSE) -> TESTEIRA | F35: M | G35: =H22*I35 -> 0
B36: 5 | D36: D1 | E36: =VLOOKUP(D36,'RESUMO_LÇ.MET.'!$A$8:$B$111,2,FALSE) -> DIVISÓRIA | F36: M2 | G36: =H22*I36*K36 -> 0
B37: 5 | D37: L1 | E37: =VLOOKUP(D37,'RESUMO_LÇ.MET.'!$A$8:$B$111,2,FALSE) -> LOUÇAS | F37: UN | G37: =H37*$H$22 -> 0
B38: 5 | D38: M1 | E38: =VLOOKUP(D38,'RESUMO_LÇ.MET.'!$A$8:$B$111,2,FALSE) -> METAIS | F38: UN | G38: =H38*$H$22 -> 0
B39: 5 | D39: A1 | E39: =VLOOKUP(D39,'RESUMO_LÇ.MET.'!$A$8:$B$111,2,FALSE) -> ACESSÓRIOS | F39: UN | G39: =H39*$H$22 -> 0

Sheet RESUMO_REV.
B1: LEVANTAMENTO DE REVESTIMENTOS INTERNOS - RESUMO
B2: OBRA:
B3: CLIENTE:
B4: LOCAL:
A5: REVESTIMENTOS DE PAREDES
A6: RB1 | B6: Chapisco interno
A7: RB2 | B7: Emboço interno + ponto de masssa
A8: RB3 | B8: Reboco interno + ponto de masssa
A9: RB4 | B9: Gesso corrido mestrado parede
A10: R1 | B10: REVESTIMENTO
A11: R2
A12: R3
A13: R4
A14: R5
A15: R6
A16: R7
A17: R8
A18: R9
A19: R10
A20: R11
A21: R12
A22: R13
... A25: FORROS / TETOS
A26: RT1 | B26: chapisco interno em tetos
A27: RT2 | B27: Emboço interno em tetos
A28: RT3 | B28: Reboco interno em tetos
A29: RT4 | B29: Gesso Corrido
A30: T1 | B30: TETO
A31: T2
A32: T3
A33: T4
A34: T5
A35: T6
A36: T7
A37: SOLEIRAS
A38: S1 | B38: SOLEIRA
A39: S2
A40: S3
A41: S3
A42: S4
A43: S5
A44: S6
A45: S7
A46: S8
A47: S9
A48: S10
A49: S11
A50: S12
A51: PISOS
A52: PB1 | B52: Camada de regularização / contrapiso e=3,0cm
A53: P1 | B53: PISO
A54: P2
A55: P3
A56: P4
A57: P5
A58: P6
A59: P7
A60: P8
A61: P9
A62: P10
A63: P11
A64: P12
A65: P13
... A72: RODAPÉS
A73: RP1 | B73: RODAPÉ
A74: RP2
A75: RP3
A76: RP4
A77: RP5
A78: RP6
A79: RP7
A80: RP8
A81: RP9
A82: RP10
A83: RP11
A84: RP12
A85: RP13
... A87: PEITORIS
A88: PT1 | B88: PEITORIL
A89: PT2
A90: PT3
A91: PT4
A92: PT5
A93: PT6
A94: PT7
A95: OBSERVAÇÕES / COMENTÁRIOS

Sheet RESUMO_ESQ.
A1: PLANILHA RESUMO: ESQUADRIAS
C2: OBRA:
C3: CLIENTE: | O3: Data:
C4: LOCAL: | O4: Levantado por:
A5: ESQUADRIAS DE MADEIRA | G5: =G6 -> 1º PAVTO | H5: =H6 -> 2º PAVTO | I5: =I6 -> 3º PAVTO | J5: =J6 -> 4º PAVTO | K5: =K6 -> 5º PAVTO | L5: =L6 -> 6º PAVTO | M5: =M6 -> 7º PAVTO | N5: =N6 -> 8º PAVTO | ... R5: =R6 -> Total
A6: Esquadria | B6: Largura | C6: Altura | D6: Descrição | E6: M2 | F6: DESCONTO | G6: 1º PAVTO | H6: 2º PAVTO | I6: 3º PAVTO | J6: 4º PAVTO | K6: 5º PAVTO | L6: 6º PAVTO | M6: 7º PAVTO | N6: 8º PAVTO | O6: 9º PAVTO | P6: 10º PAVTO | Q6: 11º PAVTO | R6: Total
A7: ESQUADRIAS DE MADEIRA
E8: =B8*C8 -> 0 | F8: =IF(E8>2,E8-2,0) -> 0 | R8: =SUM(G8:Q8) -> 0
E9: =B9*C9 -> 0 | F9: =IF(E9>2,E9-2,0) -> 0 | R9: =SUM(G9:Q9) -> 0
E10: =B10*C10 -> 0 | F10: =IF(E10>2,E10-2,0) -> 0 | R10: =SUM(G10:Q10) -> 0
E11: =B11*C11 -> 0 | F11: =IF(E11>2,E11-2,0) -> 0 | R11: =SUM(G11:Q11) -> 0
E12: =B12*C12 -> 0 | F12: =IF(E12>2,E12-2,0) -> 0 | R12: =SUM(G12:Q12) -> 0
E13: =B13*C13 -> 0 | F13: =IF(E13>2,E13-2,0) -> 0 | R13: =SUM(G13:Q13) -> 0
E14: =B14*C14 -> 0 | F14: =IF(E14>2,E14-2,0) -> 0 | R14: =SUM(G14:Q14) -> 0
E15: =B15*C15 -> 0 | F15: =IF(E15>2,E15-2,0) -> 0 | R15: =SUM(G15:Q15) -> 0
E16: =B16*C16 -> 0 | F16: =IF(E16>2,E16-2,0) -> 0 | R16: =SUM(G16:Q16) -> 0
E17: =B17*C17 -> 0 | F17: =IF(E17>2,E17-2,0) -> 0 | R17: =SUM(G17:Q17) -> 0
E18: =B18*C18 -> 0 | F18: =IF(E18>2,E18-2,0) -> 0 | R18: =SUM(G18:Q18) -> 0
E19: =B19*C19 -> 0 | F19: =IF(E19>2,E19-2,0) -> 0 | R19: =SUM(G19:Q19) -> 0
... E22: =B22*C22 -> 0 | F22: =IF(E22>2,E22-2,0) -> 0 | R22: =SUM(G22:Q22) -> 0
A23: ESQUADRIAS DE ALUMÍNIO
A24: PORTAS
E25: =B25*C25 -> 0 | F25: =IF(E25>2,E25-2,0) -> 0 | R25: =SUM(G25:Q25) -> 0
E26: =B26*C26 -> 0 | F26: =IF(E26>2,E26-2,0) -> 0 | R26: =SUM(G26:Q26) -> 0
E27: =B27*C27 -> 0 | F27: =IF(E27>2,E27-2,0) -> 0 | R27: =SUM(G27:Q27) -> 0
E28: =B28*C28 -> 0 | F28: =IF(E28>2,E28-2,0) -> 0 | R28: =SUM(G28:Q28) -> 0
E29: =B29*C29 -> 0 | F29: =IF(E29>2,E29-2,0) -> 0 | R29: =SUM(G29:Q29) -> 0
E30: =B30*C30 -> 0 | F30: =IF(E30>2,E30-2,0) -> 0 | R30: =SUM(G30:Q30) -> 0
E31: =B31*C31 -> 0 | F31: =IF(E31>2,E31-2,0) -> 0 | R31: =SUM(G31:Q31) -> 0
E32: =B32*C32 -> 0 | F32: =IF(E32>2,E32-2,0) -> 0 | R32: =SUM(G32:Q32) -> 0
E33: =B33*C33 -> 0 | F33: =IF(E33>2,E33-2,0) -> 0 | R33: =SUM(G33:Q33) -> 0
E34: =B34*C34 -> 0 | F34: =IF(E34>2,E34-2,0) -> 0 | R34: =SUM(G34:Q34) -> 0
E35: =B35*C35 -> 0 | F35: =IF(E35>2,E35-2,0) -> 0 | R35: =SUM(G35:Q35) -> 0
E36: =B36*C36 -> 0 | F36: =IF(E36>2,E36-2,0) -> 0 | R36: =SUM(G36:Q36) -> 0
... E49: =B49*C49 -> 0 | F49: =IF(E49>2,E49-2,0) -> 0 | R49: =SUM(G49:Q49) -> 0
A50: ESQUADRIAS DE ALUMÍNIO
A51: JANELAS
E52: =B52*C52 -> 0 | F52: =IF(E52>2,E52-2,0) -> 0 | R52: =SUM(G52:Q52) -> 0
E53: =B53*C53 -> 0 | F53: =IF(E53>2,E53-2,0) -> 0 | R53: =SUM(G53:Q53) -> 0
E54: =B54*C54 -> 0 | F54: =IF(E54>2,E54-2,0) -> 0 | R54: =SUM(G54:Q54) -> 0
E55: =B55*C55 -> 0 | F55: =IF(E55>2,E55-2,0) -> 0 | R55: =SUM(G55:Q55) -> 0
E56: =B56*C56 -> 0 | F56: =IF(E56>2,E56-2,0) -> 0 | R56: =SUM(G56:Q56) -> 0
E57: =B57*C57 -> 0 | F57: =IF(E57>2,E57-2,0) -> 0 | R57: =SUM(G57:Q57) -> 0
E58: =B58*C58 -> 0 | F58: =IF(E58>2,E58-2,0) -> 0 | R58: =SUM(G58:Q58) -> 0
E59: =B59*C59 -> 0 | F59: =IF(E59>2,E59-2,0) -> 0 | R59: =SUM(G59:Q59) -> 0
E60: =B60*C60 -> 0 | F60: =IF(E60>2,E60-2,0) -> 0 | R60: =SUM(G60:Q60) -> 0
E61: =B61*C61 -> 0 | F61: =IF(E61>2,E61-2,0) -> 0 | R61: =SUM(G61:Q61) -> 0
E62: =B62*C62 -> 0 | F62: =IF(E62>2,E62-2,0) -> 0 | R62: =SUM(G62:Q62) -> 0
E63: =B63*C63 -> 0 | F63: =IF(E63>2,E63-2,0) -> 0 | R63: =SUM(G63:Q63) -> 0
... E73: =B73*C73 -> 0 | F73: =IF(E73>2,E73-2,0) -> 0 | R73: =SUM(G73:Q73) -> 0
A74: ESQUADRIAS METÁLICAS
A75: PORTAS
E76: =B76*C76 -> 0 | F76: =IF(E76>2,E76-2,0) -> 0 | R76: =SUM(G76:Q76) -> 0
E77: =B77*C77 -> 0 | F77: =IF(E77>2,E77-2,0) -> 0 | R77: =SUM(G77:Q77) -> 0
E78: =B78*C78 -> 0 | F78: =IF(E78>2,E78-2,0) -> 0 | R78: =SUM(G78:Q78) -> 0
E79: =B79*C79 -> 0 | F79: =IF(E79>2,E79-2,0) -> 0 | R79: =SUM(G79:Q79) -> 0
E80: =B80*C80 -> 0 | F80: =IF(E80>2,E80-2,0) -> 0 | R80: =SUM(G80:Q80) -> 0
E81: =B81*C81 -> 0 | F81: =IF(E81>2,E81-2,0) -> 0 | R81: =SUM(G81:Q81) -> 0
E82: =B82*C82 -> 0 | F82: =IF(E82>2,E82-2,0) -> 0 | R82: =SUM(G82:Q82) -> 0
E83: =B83*C83 -> 0 | F83: =IF(E83>2,E83-2,0) -> 0 | R83: =SUM(G83:Q83) -> 0
E84: =B84*C84 -> 0 | F84: =IF(E84>2,E84-2,0) -> 0 | R84: =SUM(G84:Q84) -> 0
E85: =B85*C85 -> 0 | F85: =IF(E85>2,E85-2,0) -> 0 | R85: =SUM(G85:Q85) -> 0
E86: =B86*C86 -> 0 | F86: =IF(E86>2,E86-2,0) -> 0 | R86: =SUM(G86:Q86) -> 0
E87: =B87*C87 -> 0 | F87: =IF(E87>2,E87-2,0) -> 0 | R87: =SUM(G87:Q87) -> 0
E88: =B88*C88 -> 0 | F88: =IF(E88>2,E88-2,0) -> 0 | R88: =SUM(G88:Q88) -> 0
A89: JANELAS
E90: =B90*C90 -> 0 | F90: =IF(E90>2,E90-2,0) -> 0 | R90: =SUM(G90:Q90) -> 0
E91: =B91*C91 -> 0 | F91: =IF(E91>2,E91-2,0) -> 0 | R91: =SUM(G91:Q91) -> 0
E92: =B92*C92 -> 0 | F92: =IF(E92>2,E92-2,0) -> 0 | R92: =SUM(G92:Q92) -> 0
E93: =B93*C93 -> 0 | F93: =IF(E93>2,E93-2,0) -> 0 | R93: =SUM(G93:Q93) -> 0
E94: =B94*C94 -> 0 | F94: =IF(E94>2,E94-2,0) -> 0 | R94: =SUM(G94:Q94) -> 0
E95: =B95*C95 -> 0 | F95: =IF(E95>2,E95-2,0) -> 0 | R95: =SUM(G95:Q95) -> 0
E96: =B96*C96 -> 0 | F96: =IF(E96>2,E96-2,0) -> 0 | R96: =SUM(G96:Q96) -> 0
E97: =B97*C97 -> 0 | F97: =IF(E97>2,E97-2,0) -> 0 | R97: =SUM(G97:Q97) -> 0
E98: =B98*C98 -> 0 | F98: =IF(E98>2,E98-2,0) -> 0 | R98: =SUM(G98:Q98) -> 0
E99: =B99*C99 -> 0 | F99: =IF(E99>2,E99-2,0) -> 0 | R99: =SUM(G99:Q99) -> 0
E100: =B100*C100 -> 0 | F100: =IF(E100>2,E100-2,0) -> 0 | R100: =SUM(G100:Q100) -> 0
E101: =B101*C101 -> 0 | F101: =IF(E101>2,E101-2,0) -> 0 | R101: =SUM(G101:Q101) -> 0
... E103: =B103*C103 -> 0 | F103: =IF(E103>2,E103-2,0) -> 0 | R103: =SUM(G103:Q103) -> 0
E104: =B104*C104 -> 0 | F104: =IF(E104>2,E104-2,0) -> 0
A105: DIVERSOS
E106: =B106*C106 -> 0 | F106: =IF(E106>2,E106-2,0) -> 0 | R106: =SUM(G106:Q106) -> 0
E107: =B107*C107 -> 0 | F107: =IF(E107>2,E107-2,0) -> 0 | R107: =SUM(G107:Q107) -> 0
E108: =B108*C108 -> 0 | F108: =IF(E108>2,E108-2,0) -> 0 | R108: =SUM(G108:Q108) -> 0
E109: =B109*C109 -> 0 | F109: =IF(E109>2,E109-2,0) -> 0 | R109: =SUM(G109:Q109) -> 0
E110: =B110*C110 -> 0 | F110: =IF(E110>2,E110-2,0) -> 0 | R110: =SUM(G110:Q110) -> 0
E111: =B111*C111 -> 0 | F111: =IF(E111>2,E111-2,0) -> 0 | R111: =SUM(G111:Q111) -> 0
E112: =B112*C112 -> 0 | F112: =IF(E112>2,E112-2,0) -> 0 | R112: =SUM(G112:Q112) -> 0
E113: =B113*C113 -> 0 | F113: =IF(E113>2,E113-2,0) -> 0 | R113: =SUM(G113:Q113) -> 0
E114: =B114*C114 -> 0 | F114: =IF(E114>2,E114-2,0) -> 0 | R114: =SUM(G114:Q114) -> 0
E115: =B115*C115 -> 0 | F115: =IF(E115>2,E115-2,0) -> 0 | R115: =SUM(G115:Q115) -> 0
E116: =B116*C116 -> 0 | F116: =IF(E116>2,E116-2,0) -> 0 | R116: =SUM(G116:Q116) -> 0
E117: =B117*C117 -> 0 | F117: =IF(E117>2,E117-2,0) -> 0 | R117: =SUM(G117:Q117) -> 0
... E121: =B121*C121 -> 0 | F121: =IF(E121>2,E121-2,0) -> 0 | R121: =SUM(G121:Q121) -> 0
A122: VIDROS TEMPERADOS
E123: =B123*C123 -> 0 | F123: =IF(E123>2,E123-2,0) -> 0 | R123: =SUM(G123:Q123) -> 0
E124: =B124*C124 -> 0 | F124: =IF(E124>2,E124-2,0) -> 0 | R124: =SUM(G124:Q124) -> 0
E125: =B125*C125 -> 0 | F125: =IF(E125>2,E125-2,0) -> 0 | R125: =SUM(G125:Q125) -> 0
E126: =B126*C126 -> 0 | F126: =IF(E126>2,E126-2,0) -> 0 | R126: =SUM(G126:Q126) -> 0
E127: =B127*C127 -> 0 | F127: =IF(E127>2,E127-2,0) -> 0 | R127: =SUM(G127:Q127) -> 0
...

Sheet RESUMO_LÇ.MET.
B1: LEVANTAMENTO DE LOUÇAS, METAIS, BANCADAS E DIVISÓRIAS - RESUMO
B2: OBRA:
B3: CLIENTE:
B4: LOCAL:
A6: LOUÇAS
A8: L1 | B8: LOUÇAS
A9: L2
A10: L3
A11: L4
A12: L5
A13: L6
A14: L7
A15: L8
A16: L9
A17: L10
A18: L11
A19: L12
A20: L13
... A29: METAIS
A31: M1 | B31: METAIS
A32: M2
A33: M3
A34: M4
A35: M5
A36: M6
A37: M7
A38: M8
A39: M9
A40: M10
A41: M11
A42: M12
A43: M13
... A48: ACESSÓRIOS
A50: A1 | B50: ACESSÓRIOS
A51: A2
A52: A3
A53: A4
A54: A5
A55: A6
A56: A7
A57: A8
A58: A9
A59: A10
A60: A11
A61: A12
A62: A13
... A71: BANCADAS
A73: B1 | B73: BANCADA
A74: B2
A75: B2
A76: B2
A77: B2
A78: B2
A79: B2
A80: B2
A81: B2
A82: B3
A84: RODABANCA
A86: RB1 | B86: RODABANCA
A87: RB2
A88: RB3
A89: RB4
A90: RB5
A91: RB6
A92: RB7
A94: TESTEIRA
A96: TT1 | B96: TESTEIRA
A97: TT2
A98: TT3
A99: TT4
A100: TT5
A101: TT6
A102: TT7
A104: DIVISÓRIAS
A106: D1 | B106: DIVISÓRIA
A107: D2
A108: D3
A109: D4
A110: D5
A111: D6
A112: D7
A113: D8
A114: D9
A115: D10
A117: PRATELEIRA
A119: T1
A120: T2
... A128: OBSERVAÇÕES / COMENTÁRIOS

Sheet IMPER
B1: LEVANTAMENTO DE IMPERMEABILIZAÇÃO - RESUMO
C2: OBRA:
C3: CLIENTE:
C4: LOCAL:
A6: TIPO | F6: TOTAL
A8: PROTEÇÃO MECÂNICA
A9: I1 | B9: IMPERMEABILIZAÇÃO DE LAJE PLANA COM MANTA ASFÁLTICA 4 MM INCLUSIVE PROTEÇÃO MECÂNICA
A10: I2 | B10: IMPERMEABILIZAÇÃO DE JARDINEIRAS COM MANTA ANTI RAIZ 3 MM INCLUSIVE CAMADA DE REGULARIZAÇÃO E PROTEÇÃO MECÂNICA
A11: I3 | B11: IMPERMEABILIZAÇÃO DE ÁREAS MOLHADAS COM VIAPLUS 1000
A12: I4 | B12: IMPERMEABILIZAÇÃO DE LAJE PLANA COM MANTA ASFÁLTICA 4 MM INCLUSIVE CAMADA DE REGULARIZAÇÃO E PROTEÇÃO MECÂNICA
A13: I5 | B13: Impermeabilização de piso com manta asfáltica aluminizada 3mm
A14: I6 | B14: impermeabilização da laje com manta asfáltica aluminizada - Vestiários
A15: I7
A16: I8
A17: I9
A18: I10
A20: TOTAL GERAL | F20: =SUM(F8:F19) -> 0
A22: OBSERVAÇÕES / COMENTÁRIOS

Sheet ESTUDO PRAZO
A1: CONSTRUTORA ULISSES - ED. MONTEVIDÉU - R00
A3: ESTUDO LOCAÇÃO DE BANDEJAS DE SEGURANÇA
R5: EXECUÇÃO LAJE (DIAS)
A7: Topo caixa d'água | R7: PRAZO | S7: 14
A9: Caixa d'água | R9: PRAZO | S9: 14
A11: Cobertura | R11: PRAZO | S11: 14
A13: 11º nível | R13: PRAZO | S13: 21
A15: 10º nível | R15: PRAZO | S15: =21+9 -> 30
A17: 9º nível | R17: PRAZO | S17: =21+9 -> 30
A19: 8º nível | R19: PRAZO | S19: =21+9 -> 30
A21: 7º nível | R21: PRAZO | S21: =21+9 -> 30
A23: 6º nível | R23: PRAZO | S23: =21+9 -> 30
A25: 5º nível | R25: PRAZO | S25: =21+9 -> 30
A27: 4º nível | R27: PRAZO | S27: =21+9 -> 30
A29: 3º nível | R29: PRAZO | S29: 30
A31: 2º nível - Téreo | R31: PRAZO | S31: 30
A33: 1º nível
E40: Bandeja L=250cm | X40: =EQUIPAMENTO!K7 -> 45356 | Y40: 45447 | Z40: =Y40=X40 -> FALSE
E41: Bandeja L=150cm - 1 | O41: PRAZO PARA EXECUÇÃO DA ESTRUTURA + ALVENARIA | S41: =SUM(S7:S34)+30 -> 363 | T41: dias | U41: =ROUNDUP(S41/30,0) -> 13 | V41: meses | X41: =$X$40+S41 -> 45719
E42: Bandeja L=150cm - 2
O43: INÍCIO DA BANDEJA DE 250CM | S43: =SUM(S27:S31) -> 90 | T43: dias | U43: =ROUNDUP(S43/30,0) -> 3 | V43: meses | X43: =$X$40+S43 -> 45446
O45: TÉRMINO DA BANDEJA DE 250CM | S45: =SUM(S7:S27)+90 -> 363 | T45: dias | U45: =ROUNDUP(S45/30,0) -> 13 | V45: meses | X45: =$X$40+S45 -> 45719
O47: INÍCIO DA BANDEJA 01 DE 150CM | S47: =SUM(S21:S31) -> 180 | T47: dias | U47: =ROUNDUP(S47/30,0) -> 6 | V47: meses | X47: =$X$40+S47 -> 45536
O49: TÉRMINO DA BANDEJA 01 DE 150CM | S49: =SUM(S9:S31) -> 319 | T49: dias | U49: =ROUNDUP(S49/30,0) -> 11 | V49: meses | X49: =$X$40+S49 -> 45675
O51: INÍCIO DA BANDEJA 02 DE 150CM | S51: =SUM(S19:S31) -> 210 | T51: dias | U51: =ROUNDUP(S51/30,0) -> 7 | V51: meses | X51: =$X$40+S51 -> 45566
O53: TÉRMINO DA BANDEJA 02 DE 150CM | S53: =SUM(S7:S31) -> 333 | T53: dias | U53: =ROUNDUP(S53/30,0) -> 12 | V53: meses | X53: =$X$40+S53 -> 45689

Sheet MAO DE OBRA
E2: OBRA: | F2: ED. MONTEVIDÉU
E3: CLIENTE: | F3: CONSTRUTORA ULISSES
E4: QUADRO DE MÃO DE OBRA FIXA DA OBRA - CUSTO INDIRETO - PREVISTO
E5: TERRAPLENAGEM, CONTENÇÃO E FUNDAÇÃO | L5: ESTRUTURA + ALVENARIA | Y5: ACABAMENTOS + FACHADA
B6: DESCRIÇÃO | C6: SALÁRIOS | E6: MÊS 01 | F6: MÊS 02 | G6: MÊS 03 | H6: MÊS 04 | I6: MÊS 05 | J6: MÊS 06 | K6: MÊS 07 | L6: MÊS 08 | M6: MÊS 09 | N6: MÊS 10 | O6: MÊS 11 | P6: MÊS 12 | Q6: MÊS 13 | R6: MÊS 14 | S6: MÊS 15 | T6: MÊS 16 | U6: MÊS 17 | V6: MÊS 18 | W6: MÊS 19 | X6: MÊS 20 | Y6: MÊS 21 | Z6: MÊS 22 | AA6: MÊS 23 | AB6: MÊS 24 | AC6: MÊS 25 | AD6: MÊS 26 | AE6: MÊS 27 | AF6: MÊS 28 | AG6: MÊS 29 | AH6: MÊS 30 | AI6: MÊS 31 | AJ6: MÊS 32 | AK6: MÊS 33 | AL6: MÊS 34 | AM6: MÊS 35 | AN6: MÊS 36 | AP6: TOTAL
E7: 45139 | F7: =E7+31 -> 45170 | G7: =F7+31 -> 45201 | H7: =G7+31 -> 45232 | I7: =H7+31 -> 45263 | J7: =I7+31 -> 45294 | K7: =J7+31 -> 45325 | L7: =K7+31 -> 45356 | M7: =L7+31 -> 45387 | ... AN7: =AM7+31 -> 46224
B9: ENGENHEIRO RESIDENTE - PJ | C9: 18000 | E9: 1 | F9: 1 | G9: 1 | H9: 1 | I9: 1 | J9: 1 | K9: 1 | L9: 1 | M9: 1 | N9: 1 | O9: 1 | P9: 1 | Q9: 1 | R9: 1 | S9: 1 | T9: 1 | U9: 1 | V9: 1 | W9: 1 | X9: 1 | Y9: 1 | Z9: 1 | AA9: 1 | AB9: 1 | AC9: 1 | AD9: 1 | AE9: 1 | AF9: 1 | AG9: 1 | AH9: 1 | AI9: 1 | AJ9: 1 | AK9: 1 | AL9: 1 | AM9: 1 | AN9: 1 | AP9: =SUM(E9:AN9) -> 36 | AQ9: =C9*AP9 -> 648000
B10: TÉCNICO DE SEGURANÇA DO TRABALHO - VISITAS | C10: 6160.89 | E10: 0.25 | F10: 0.25 | G10: 0.25 | H10: 0.25 | I10: 0.25 | J10: 0.25 | K10: 0.25 | L10: 0.25 | M10: 0.25 | N10: 0.25 | O10: 0.25 | P10: 0.25 | Q10: 0.25 | R10: 0.25 | S10: 0.25 | T10: 0.25 | U10: 0.25 | V10: 0.25 | W10: 0.25 | X10: 0.25 | Y10: 0.25 | Z10: 0.25 | AA10: 0.25 | AB10: 0.25 | AC10: 0.25 | AD10: 0.25 | AE10: 0.25 | AF10: 0.25 | AG10: 0.25 | AH10: 0.25 | AI10: 0.25 | AJ10: 0.25 | AK10: 0.25 | AL10: 0.25 | AM10: 0.25 | AN10: 0.25 | AP10: =SUM(E10:AN10) -> 9 | AQ10: =C10*AP10 -> 55448.01
B11: ESTAGIÁRIO | C11: 2380 | G11: 1 | H11: 1 | I11: 1 | J11: 1 | K11: 1 | L11: 1 | M11: 1 | N11: 1 | O11: 1 | P11: 1 | Q11: 1 | R11: 1 | S11: 1 | T11: 1 | U11: 1 | V11: 1 | W11: 1 | X11: 1 | Y11: 1 | Z11: 1 | AA11: 1 | AB11: 1 | AC11: 1 | AD11: 1 | AE11: 1 | AF11: 1 | AG11: 1 | AH11: 1 | AI11: 1 | AJ11: 1 | AK11: 1 | AL11: 1 | AM11: 1 | AN11: 1 | AP11: =SUM(E11:AN11) -> 34 | AQ11: =C11*AP11 -> 80920
B12: MESTRE DE OBRA | C12: 16160.89 | E12: 1 | F12: 1 | G12: 1 | H12: 1 | I12: 1 | J12: 1 | K12: 1 | L12: 1 | M12: 1 | N12: 1 | O12: 1 | P12: 1 | Q12: 1 | R12: 1 | S12: 1 | T12: 1 | U12: 1 | V12: 1 | W12: 1 | X12: 1 | Y12: 1 | Z12: 1 | AA12: 1 | AB12: 1 | AC12: 1 | AD12: 1 | AE12: 1 | AF12: 1 | AG12: 1 | AH12: 1 | AI12: 1 | AJ12: 1 | AK12: 1 | AL12: 1 | AM12: 1 | AN12: 1 | AP12: =SUM(E12:AN12) -> 36 | AQ12: =C12*AP12 -> 581792.04
B13: ADMINISTRATIVO | C13: 6717.332 | E13: 1 | F13: 1 | G13: 1 | H13: 1 | I13: 1 | J13: 1 | K13: 1 | L13: 1 | M13: 1 | N13: 1 | O13: 1 | P13: 1 | Q13: 1 | R13: 1 | S13: 1 | T13: 1 | U13: 1 | V13: 1 | W13: 1 | X13: 1 | Y13: 1 | Z13: 1 | AA13: 1 | AB13: 1 | AC13: 1 | AD13: 1 | AE13: 1 | AF13: 1 | AG13: 1 | AH13: 1 | AI13: 1 | AJ13: 1 | AK13: 1 | AL13: 1 | AM13: 1 | AN13: 1 | AP13: =SUM(E13:AN13) -> 36 | AQ13: =C13*AP13 -> 241823.95
B14: ALMOXARIFE | C14: 6160.89 | G14: 1 | H14: 1 | I14: 1 | J14: 1 | K14: 1 | L14: 1 | M14: 1 | N14: 1 | O14: 1 | P14: 1 | Q14: 1 | R14: 1 | S14: 1 | T14: 1 | U14: 1 | V14: 1 | W14: 1 | X14: 1 | Y14: 1 | Z14: 1 | AA14: 1 | AB14: 1 | AC14: 1 | AD14: 1 | AE14: 1 | AF14: 1 | AG14: 1 | AH14: 1 | AI14: 1 | AJ14: 1 | AK14: 1 | AL14: 1 | AM14: 1 | AN14: 1 | AP14: =SUM(E14:AN14) -> 34 | AQ14: =C14*AP14 -> 209470.26
B15: ENCARREGADO GERAL | C15: 12160.89 | Y15: 1 | Z15: 1 | AA15: 1 | AB15: 1 | AC15: 1 | AD15: 1 | AE15: 1 | AF15: 1 | AG15: 1 | AH15: 1 | AI15: 1 | AJ15: 1 | AK15: 1 | AL15: 1 | AM15: 1 | AN15: 1 | AP15: =SUM(E15:AN15) -> 16 | AQ15: =C15*AP15 -> 194574.24
B16: OPERADOR DE ELEVADOR CREMALHEIRA | C16: 6717.332 | E16: =EQUIPAMENTO!D21 -> 0 | F16: =EQUIPAMENTO!E21 -> 0 | G16: =EQUIPAMENTO!F21 -> 0 | H16: =EQUIPAMENTO!G21 -> 0 | I16: =EQUIPAMENTO!H21 -> 0 | J16: =EQUIPAMENTO!I21 -> 0 | K16: =EQUIPAMENTO!J21 -> 0 | L16: =EQUIPAMENTO!K21 -> 0 | ... AN16: =EQUIPAMENTO!AM21 -> 0 | AP16: =SUM(E16:AN16) -> 23 | AQ16: =C16*AP16 -> 154498.64
B17: OPERADOR DE BETONEIRA | C17: 6717.332 | E17: =EQUIPAMENTO!D13 -> 0 | F17: =EQUIPAMENTO!E13 -> 1 | G17: =EQUIPAMENTO!F13 -> 1 | H17: =EQUIPAMENTO!G13 -> 1 | I17: =EQUIPAMENTO!H13 -> 1 | J17: =EQUIPAMENTO!I13 -> 1 | K17: =EQUIPAMENTO!J13 -> 1 | L17: =EQUIPAMENTO!K13 -> 1 | ... AN17: =EQUIPAMENTO!AM13 -> 0 | AP17: =SUM(E17:AN17) -> 28 | AQ17: =C17*AP17 -> 188085.3
B18: AUXILIAR DE BETONEIRA (SERVENTE) | C18: 4857.4555 | E18: =E17 -> 0 | F18: =F17 -> 1 | G18: =G17 -> 1 | H18: =H17 -> 1 | I18: =I17 -> 1 | J18: =J17 -> 1 | K18: =K17 -> 1 | L18: =L17 -> 1 | ... AN18: =AN17 -> 0 | AP18: =SUM(E18:AN18) -> 28 | AQ18: =C18*AP18 -> 136008.75
B19: PEDREIRO DE APOIO | C19: 6717.332 | E19: 1 | F19: 1 | G19: 1 | H19: 1 | I19: 1 | J19: 1 | K19: 1 | L19: 1 | M19: 1 | N19: 1 | O19: 1 | P19: 1 | Q19: 1 | R19: 1 | S19: 1 | T19: 1 | U19: 1 | V19: 1 | W19: 1 | X19: 1 | Y19: 1 | Z19: 1 | AA19: 1 | AB19: 1 | AC19: 1 | AD19: 1 | AE19: 1 | AF19: 1 | AG19: 1 | AH19: 1 | AI19: 1 | AJ19: 1 | AK19: 1 | AL19: 1 | AM19: 1 | AN19: 1 | AP19: =SUM(E19:AN19) -> 36 | AQ19: =C19*AP19 -> 241823.95
B20: BOMBEIRO/ELETRICISTA DE APOIO | C20: 6717.332 | E20: 1 | F20: 1 | G20: 1 | H20: 1 | I20: 1 | J20: 1 | K20: 1 | L20: 1 | M20: 1 | N20: 1 | O20: 1 | P20: 1 | Q20: 1 | R20: 1 | S20: 1 | T20: 1 | U20: 1 | V20: 1 | W20: 1 | X20: 1 | Y20: 1 | Z20: 1 | AA20: 1 | AB20: 1 | AC20: 1 | AD20: 1 | AE20: 1 | AF20: 1 | AG20: 1 | AH20: 1 | AI20: 1 | AJ20: 1 | AK20: 1 | AL20: 1 | AM20: 1 | AN20: 1 | AP20: =SUM(E20:AO20) -> 36 | AQ20: =C20*AP20 -> 241823.95
B21: CARPINTEIRO DE APOIO E SEGURANÇA | C21: 6717.332 | E21: 1 | F21: 1 | G21: 1 | H21: 1 | I21: 1 | J21: 1 | K21: 1 | L21: 1 | M21: 1 | N21: 1 | O21: 1 | P21: 1 | Q21: 1 | R21: 1 | S21: 1 | T21: 1 | U21: 1 | V21: 1 | W21: 1 | X21: 1 | AP21: =SUM(E21:AN21) -> 20 | AQ21: =C21*AP21 -> 134346.64
B22: SERVENTE DE APOIO / LIMPEZA / CARGA E DESCARGA | C22: 4857.4555 | E22: 2 | F22: 2 | G22: 2 | H22: 2 | I22: 2 | J22: 2 | K22: 2 | L22: 4 | M22: 4 | N22: 4 | O22: 4 | P22: 4 | Q22: 4 | R22: 4 | S22: 4 | T22: 4 | U22: 4 | V22: 4 | W22: 4 | X22: 4 | Y22: 4 | Z22: 4 | AA22: 4 | AB22: 4 | AC22: 4 | AD22: 4 | AE22: 4 | AF22: 4 | AG22: 4 | AH22: 4 | AI22: 4 | AJ22: 4 | AK22: 4 | AL22: 4 | AM22: 4 | AN22: 4 | AP22: =SUM(E22:AN22) -> 130 | AQ22: =C22*AP22 -> 631469.21
B23: VIGIA | C23: 4972.3302 | E23: 2 | F23: 2 | G23: 2 | H23: 2 | I23: 2 | J23: 2 | K23: 2 | L23: 2 | M23: 2 | N23: 2 | O23: 2 | P23: 2 | Q23: 2 | R23: 2 | S23: 2 | T23: 2 | U23: 2 | V23: 2 | W23: 2 | X23: 2 | Y23: 2 | Z23: 2 | AA23: 2 | AB23: 2 | AC23: 2 | AD23: 2 | AE23: 2 | AF23: 2 | AG23: 2 | AH23: 2 | AI23: 2 | AJ23: 2 | AK23: 2 | AL23: 2 | AM23: 2 | AN23: 2 | AP23: =SUM(E23:AN23) -> 72 | AQ23: =C23*AP23 -> 358007.78
B24: PORTEIRO | C24: 4857.4555 | E24: 1 | F24: 1 | G24: 1 | H24: 1 | I24: 1 | J24: 1 | K24: 1 | L24: 1 | M24: 1 | N24: 1 | O24: 1 | P24: 1 | Q24: 1 | R24: 1 | S24: 1 | T24: 1 | U24: 1 | V24: 1 | W24: 1 | X24: 1 | Y24: 1 | Z24: 1 | AA24: 1 | AB24: 1 | AC24: 1 | AD24: 1 | AE24: 1 | AF24: 1 | AG24: 1 | AH24: 1 | AI24: 1 | AJ24: 1 | AK24: 1 | AL24: 1 | AM24: 1 | AN24: 1 | AP24: =SUM(E24:AN24) -> 36 | AQ24: =C24*AP24 -> 174868.4
B26: QUANTIDADE TOTAL | E26: =SUM(E8:E24) -> 11.25 | F26: =SUM(F8:F24) -> 13.25 | G26: =SUM(G8:G24) -> 15.25 | H26: =SUM(H8:H24) -> 15.25 | I26: =SUM(I8:I24) -> 15.25 | J26: =SUM(J8:J24) -> 15.25 | K26: =SUM(K8:K24) -> 15.25 | L26: =SUM(L8:L24) -> 17.25 | ... AN26: =SUM(AN8:AN24) -> 15.25 | AP26: =SUM(AP9:AP24) -> 610 | AQ26: =SUM(AQ9:AQ24) -> 4272961.1
AQ27: =AQ26/36 -> 118693.36
AQ28: =AQ27*0.012 -> 1424.3204

Sheet EQUIPAMENTO
D2: OBRA: | E2: ED. MONTEVIDÉU
D3: CLIENTE: | E3: CONSTRUTORA ULISSES
D4: QUADRO DE EQUIPAMENTO FIXO DA OBRA - CUSTO INDIRETO - PREVISTO
D5: TERRAPLENAGEM, CONTENÇÃO E FUNDAÇÃO | K5: ESTRUTURA + ALVENARIA | X5: ACABAMENTOS + FACHADA
B6: DESCRIÇÃO | D6: MÊS 01 | E6: MÊS 02 | F6: MÊS 03 | G6: MÊS 04 | H6: MÊS 05 | I6: MÊS 06 | J6: MÊS 07 | K6: MÊS 08 | L6: MÊS 09 | M6: MÊS 10 | N6: MÊS 11 | O6: MÊS 12 | P6: MÊS 13 | Q6: MÊS 14 | R6: MÊS 15 | S6: MÊS 16 | T6: MÊS 17 | U6: MÊS 18 | V6: MÊS 19 | W6: MÊS 20 | X6: MÊS 21 | Y6: MÊS 22 | Z6: MÊS 23 | AA6: MÊS 24 | AB6: MÊS 25 | AC6: MÊS 26 | AD6: MÊS 27 | AE6: MÊS 28 | AF6: MÊS 29 | AG6: MÊS 30 | AH6: MÊS 31 | AI6: MÊS 32 | AJ6: MÊS 33 | AK6: MÊS 34 | AL6: MÊS 35 | AM6: MÊS 36 | AO6: TOTAL
D7: 45139 | E7: =D7+31 -> 45170 | F7: =E7+31 -> 45201 | G7: =F7+31 -> 45232 | H7: =G7+31 -> 45263 | I7: =H7+31 -> 45294 | J7: =I7+31 -> 45325 | K7: =J7+31 -> 45356 | L7: =K7+31 -> 45387 | ... AM7: =AL7+31 -> 46224
B9: BEBEDOURO (COMPRA) | AO9: 4
B10: ESTUFA ELÉTRICA (COMPRAR) | AO10: 2
B11: RELÓGIO DE PONTO (COMPRA) | AO11: 1
B12: RÁDIO COMUNICADOR (ALUGUEL) | D12: 4 | E12: 4 | F12: 4 | G12: 4 | H12: 4 | I12: 4 | J12: 4 | K12: 4 | L12: 4 | M12: 4 | N12: 4 | O12: 4 | P12: 4 | Q12: 4 | R12: 4 | S12: 4 | T12: 4 | U12: 4 | V12: 4 | W12: 4 | X12: 4 | Y12: 4 | Z12: 4 | AA12: 4 | AB12: 4 | AC12: 4 | AD12: 4 | AE12: 4 | AF12: 4 | AG12: 4 | AH12: 4 | AI12: 4 | AJ12: 4 | AK12: 4 | AL12: 4 | AM12: 4 | AO12: =SUM(D12:AM12) -> 144
B13: BETONEIRA 420 LITROS | E13: 1 | F13: 1 | G13: 1 | H13: 1 | I13: 1 | J13: 1 | K13: 1 | L13: 1 | M13: 1 | N13: 1 | O13: 1 | P13: 1 | Q13: 1 | R13: 1 | S13: 1 | T13: 1 | U13: 1 | V13: 1 | W13: 1 | X13: 1 | Y13: 1 | Z13: 1 | AA13: 1 | AB13: 1 | AC13: 1 | AD13: 1 | AE13: 1 | AF13: 1 | AO13: =SUM(D13:AM13) -> 28
B14: ARGAMASSADEIRA | X14: 2 | Y14: 2 | Z14: 2 | AA14: 2 | AB14: 2 | AC14: 2 | AD14: 2 | AE14: 2 | AF14: 2 | AG14: 2 | AH14: 2 | AI14: 2 | AJ14: 2 | AK14: 2 | AL14: 2 | AO14: =SUM(D14:AM14) -> 30
B15: MOTOR VIBRADOR + MANGOTE | F15: 3 | G15: 3 | H15: 3 | I15: 3 | J15: 3 | K15: 3 | L15: 3 | M15: 3 | N15: 3 | O15: 3 | P15: 3 | Q15: 3 | R15: 3 | S15: 3 | T15: 3 | U15: 3 | V15: 3 | AO15: =SUM(D15:AM15) -> 51
B16: SERRA ELÉTRICA MANUAL | E16: 1 | F16: 1 | G16: 1 | H16: 1 | I16: 1 | J16: 1 | K16: 1 | L16: 1 | M16: 1 | N16: 1 | O16: 1 | P16: 1 | Q16: 1 | R16: 1 | S16: 1 | T16: 1 | U16: 1 | V16: 1 | AO16: =SUM(D16:AM16) -> 18
B17: SERRA ELÉTRICA BANCADA | E17: 1 | F17: 1 | G17: 1 | H17: 1 | I17: 1 | J17: 1 | K17: 1 | L17: 1 | M17: 1 | N17: 1 | O17: 1 | P17: 1 | Q17: 1 | R17: 1 | S17: 1 | T17: 1 | U17: 1 | V17: 1 | W17: 1 | X17: 1 | Y17: 1 | AO17: =SUM(D17:AM17) -> 21
B18: COMPACTADOR CM20 TIPO SAPO MECÂNICO | F18: 1 | G18: 1 | H18: 1 | I18: 1 | J18: 1 | AK18: 1 | AL18: 1 | AO18: =SUM(D18:AM18) -> 7
B19: MÁQUINA DE CORTAR FERRO - policorte | E19: 1 | F19: 1 | G19: 1 | H19: 1 | I19: 1 | J19: 1 | K19: 1 | L19: 1 | M19: 1 | N19: 1 | O19: 1 | P19: 1 | Q19: 1 | R19: 1 | S19: 1 | T19: 1 | U19: 1 | V19: 1 | W19: 1 | AO19: =SUM(D19:AM19) -> 19
B20: GUINCHO DE COLUNA + CABO | M20: 1 | N20: 1 | O20: 1 | P20: 1 | Q20: 1 | R20: 1 | S20: 1 | T20: 1 | U20: 1 | V20: 1 | W20: 1 | AO20: =SUM(D20:AM20) -> 11
B21: ELEVADOR CREMALHEIRA - CABINE DUPLA | N21: 1 | O21: 1 | P21: 1 | Q21: 1 | R21: 1 | S21: 1 | T21: 1 | U21: 1 | V21: 1 | W21: 1 | X21: 1 | Y21: 1 | Z21: 1 | AA21: 1 | AB21: 1 | AC21: 1 | AD21: 1 | AE21: 1 | AF21: 1 | AG21: 1 | AH21: 1 | AI21: 1 | AJ21: 1 | AO21: =SUM(D21:AM21) -> 23
B22: FURADEIRA DE IMPACTO | D22: 2 | E22: 2 | F22: 2 | G22: 2 | H22: 2 | I22: 2 | J22: 2 | K22: 2 | L22: 2 | M22: 2 | N22: 2 | O22: 2 | P22: 2 | Q22: 2 | R22: 2 | S22: 2 | T22: 2 | U22: 2 | V22: 2 | W22: 2 | X22: 2 | Y22: 2 | Z22: 2 | AA22: 2 | AB22: 2 | AC22: 2 | AD22: 2 | AE22: 2 | AF22: 2 | AG22: 2 | AH22: 2 | AI22: 2 | AJ22: 2 | AK22: 2 | AL22: 2 | AM22: 2 | AO22: =SUM(D22:AM22) -> 72
B23: FURADEIRA BATEDEIRA | X23: 3 | Y23: 3 | Z23: 3 | AA23: 3 | AB23: 3 | AC23: 3 | AD23: 3 | AE23: 3 | AF23: 3 | AG23: 3 | AH23: 3 | AI23: 3 | AJ23: 3 | AK23: 3 | AL23: 3 | AO23: =SUM(D23:AM23) -> 45
B24: SERRA MÁRMORE - MAKITA | X24: 3 | Y24: 3 | Z24: 3 | AA24: 3 | AB24: 3 | AC24: 3 | AD24: 3 | AE24: 3 | AF24: 3 | AG24: 3 | AH24: 3 | AI24: 3 | AJ24: 3 | AK24: 3 | AL24: 3 | AO24: =SUM(D24:AM24) -> 45
B25: LIXADEIRA PORTÁTIL | D25: 2 | E25: 2 | F25: 2 | G25: 2 | H25: 2 | I25: 2 | J25: 2 | K25: 2 | L25: 2 | M25: 2 | N25: 2 | O25: 2 | P25: 2 | Q25: 2 | R25: 2 | S25: 2 | T25: 2 | U25: 2 | V25: 2 | W25: 2 | X25: 2 | Y25: 2 | Z25: 2 | AA25: 2 | AB25: 2 | AO25: =SUM(D25:AM25) -> 50
B26: PISTOLA HILT / WALSIVA - FINCA PINO | K26: 1 | L26: 1 | M26: 1 | N26: 1 | O26: 1 | P26: 1 | Q26: 1 | R26: 1 | S26: 1 | T26: 1 | U26: 1 | V26: 1 | W26: 1 | AO26: =SUM(D26:AM26) -> 13
B27: MARTELETE ROMPEDOR 15 KG | F27: 1 | G27: 1 | H27: 1 | I27: 1 | J27: 1 | K27: 1 | L27: 1 | M27: 1 | N27: 1 | O27: 1 | P27: 1 | Q27: 1 | R27: 1 | S27: 1 | T27: 1 | U27: 1 | V27: 1 | W27: 1 | AK27: 1 | AL27: 1 | AO27: =SUM(D27:AM27) -> 20
B28: ESMERILHADEIRA | D28: 3 | E28: 3 | F28: 3 | G28: 3 | H28: 3 | I28: 3 | J28: 3 | K28: 3 | L28: 3 | M28: 3 | N28: 3 | O28: 3 | P28: 3 | Q28: 3 | R28: 3 | S28: 3 | T28: 3 | U28: 3 | V28: 3 | W28: 3 | AO28: =SUM(D28:AM28) -> 60
B29: RETRO ESCAVADEIRA | D29: 1 | E29: 1 | F29: 1 | G29: 1 | AO29: =SUM(D29:AM29) -> 4
B30: CAMINHÃO MUNCK (DIÁRIA) | AO30: 10
B31: APARALIXO PRIMÁRIO (PEÇA) | M31: 1 | N31: 1 | O31: 1 | P31: 1 | Q31: 1 | R31: 1 | S31: 1 | T31: 1 | U31: 1 | V31: 1 | W31: 1 | AO31: =SUM(D31:AM31) -> 11
B32: APARALIXO SECUNDÁRIO (PEÇA) - 01 | R32: 1 | S32: 1 | T32: 1 | U32: 1 | V32: 1 | AO32: =SUM(D32:AM32) -> 5
B33: APARALIXO SECUNDÁRIO (PEÇA) - 02 | S33: 1 | T33: 1 | U33: 1 | V33: 1 | AO33: =SUM(D33:AM33) -> 4
B34: LOCAÇÃO DE LEVE SUSPENSO (BALANCIM ELÉTRICO) | AB34: 1 | AC34: 1 | AD34: 1 | AE34: 1 | AF34: 1 | AG34: 1 | AH34: 1 | AO34: =SUM(D34:AM34) -> 7
B35: LOCAÇÃO DE ANDAIME FACHADEIRO | Z35: 1 | AA35: 1 | AB35: 1 | AC35: 1 | AD35: 1 | AO35: =SUM(D35:AM35) -> 5
B36: CAMINHÃO PIPA (VIAGEM) - 01 POR SEMANA | E36: =1*4 -> 4 | AN36: 100 | AO36: =SUM(D36:AM36) -> 4
B38: QUANTIDADE TOTAL | D38: =SUM(D8:D36) -> 12 | E38: =SUM(E8:E36) -> 20 | F38: =SUM(F8:F36) -> 21 | G38: =SUM(G8:G36) -> 21 | H38: =SUM(H8:H36) -> 20 | I38: =SUM(I8:I36) -> 20 | J38: =SUM(J8:J36) -> 20 | K38: =SUM(K8:K36) -> 20 | ... AM38: =SUM(AM8:AM36) -> 6 | AO38: =SUM(AO9:AO36) -> 714

Sheet ANDAIMES
G3: OBRA: | H3: ED. MONTEVIDÉU
G4: CLIENTE: | H4: CONSTRUTORA ULISSES
Z5: RESUMO
E6: 3º AO 6º PAVIMENTO | AA6: BALANCINHO | AB6: FACHADEIRO
Z7: TOTAL: | AA7: =SUM(M44,M78,M108,M138) -> 40 | AB7: =SUM(P44,P78,P108,P138,AB11,AB12) -> 1848.9692
Z8: LOCAR: | AA8: =AA7/2 -> 20 | AB8: =AB7/2 -> 924.4846
G9: =ROUNDUP(17.07/5,0) -> 4 | O9: =ROUNDUP(17.07/5,0) -> 4
AA10: EXTRAS
AA11: FACHADA RUA BUENOS AIRES | AB11: =23.91*7.08 -> 169.2828
D12: =ROUNDUP(19.63/4,0) -> 5 | V12: =ROUNDUP(19.63/4,0) -> 5 | AA12: MUROS LATERAIS | AB12: =((73.93*4.68)+(85.25*5.88)) -> 847.2624
Z26: =(17.07+17.07+19.63+7+19.63+7+7.63)*12.84 -> 1220.1852
G40: =7/7 -> 1 | M40: =ROUNDDOWN(7.63/2,0) -> 3 | Q40: =7/7 -> 1
I43: ANDAIME SUSPENSO | L43: BALANCINHO | O43: FACHADEIRO
I44: ANDAIME FACHADEIRO | L44: TOTAL: | M44: =SUM(G9,O9,V12,Q40,M40,D12,G40) -> 23 | O44: TOTAL: | P44: =(3.24+7.4+7.4)*12.84 -> 231.6336
E47: 7º AO 10º PAVIMENTO
G50: =ROUNDUP(11.35/6,0) -> 2 | O50: =ROUNDUP(11.35/6,0) -> 2
D53: =ROUNDUP(12.9/4,0) -> 4 | V53: =ROUNDUP(12.9/4,0) -> 4
Z63: =(11.35+11.35+12.9+12.9+28.46)*10.2 -> 784.992
G74: =ROUNDUP(28.46/6,0) -> 5
I77: ANDAIME SUSPENSO | L77: BALANCINHO | O77: FACHADEIRO
I78: ANDAIME FACHADEIRO | L78: TOTAL: | M78: =SUM(G50,O50,V53,G74,D53) -> 17 | O78: TOTAL: | P78: =3.08*10.2 -> 31.416
E81: 10º PAVIMENTO A COBERTURA
G84: =ROUNDUP(25.8/6,0) -> 5
F88: =ROUNDUP(7.46/6,0) -> 2 | V88: =ROUNDUP(7.46/6,0) -> 2
Z91: =(25.8+25.8+7.46+7.46)*5.94 -> 395.1288
G104: =ROUNDUP(25.8/6,0) -> 5
I107: ANDAIME SUSPENSO | L107: BALANCINHO | O107: FACHADEIRO
I108: ANDAIME FACHADEIRO | L108: TOTAL: | O108: TOTAL: | P108: =66.61*7.04 -> 468.9344
E111: BARRILETE / CAIXA D'ÁGUA
G114: 0
F118: 0 | V118: 0
G134: 0
I137: ANDAIME SUSPENSO | L137: BALANCINHO | O137: FACHADEIRO
I138: ANDAIME FACHADEIRO | L138: TOTAL: | M138: =SUM(G114,V118,G134,F118) -> 0 | O138: TOTAL: | P138: =22.32*4.5 -> 100.44

Sheet cpu_10013
A1: Codigo | B1: DescricaoAbreviada | C1: Unidade | D1: ProducaoEquipe | E1: OrigemComposicao | F1: TipoItemComposicao | G1: CódigoDoInsumo/ComposicaoAuxiliar | H1: DescricaoAbreviadaInsumo/ComposicaoAuxiliar | I1: UnidadeInsumo/ComposicaoAux | J1: Indice | K1: GrupoDoInsumo | L1: OrigemInsumosComposicoesAuxiliares
A3: CB0202 | B3: DEMOLIÇÃO DE ALVENARIA DE TIJOLO COMUM SEM REAPROVEIT. | C3: M3 | D3: 1 | E3: 0 | F3: I | G3: IH9000 | H3: PEDREIRO (PLANEJAMENTO) | I3: H | J3: 0.45 | K3: H | L3: 0
D4: 0 | F4: I | G4: IH9001 | H4: SERVENTE (PLANEJAMENTO) | I4: H | J4: 4.5 | K4: H | L4: 0
D5: 0 | F5: I | G5: IS0361 | H5: EMPREITEIRO DEMOLIÇÃO DE ALVENARIA | I5: M3 | J5: 1 | K5: S | L5: 0
A6: CB0206 | B6: DEMOLIÇÃO DE CONCRETO ARMADO C/ UTILIZAÇÃO MARTELETE-MENSAL | C6: M3 | D6: 1 | E6: 0 | F6: I | G6: IH1901 | H6: SERVENTE (ENCARGOS INCLUSOS) | I6: H | J6: 16 | K6: H | L6: 0
A7: CB0216 | B7: DEMOLIÇÃO DE PISO CIMENTADO SOBRE LASTRO DE CONCRETO | C7: M3 | D7: 1 | E7: 0 | F7: I | G7: IH1601 | H7: PEDREIRO (ENCARGOS INCLUSOS) | I7: H | J7: 1.3 | K7: H | L7: 0
D8: 0 | F8: I | G8: IH1901 | H8: SERVENTE (ENCARGOS INCLUSOS) | I8: H | J8: 13 | K8: H | L8: 0
A9: CB0502 | B9: DRENO COM BRITA No 2 E 3 - FORNECIMENTO E APLICAÇÃO | C9: M3 | D9: 1 | E9: 0 | F9: I | G9: IH1601 | H9: PEDREIRO (ENCARGOS INCLUSOS) | I9: H | J9: 0.5 | K9: H | L9: 0
D10: 0 | F10: I | G10: IM0305 | H10: BRITA 1 | I10: M3 | J10: 1.05 | K10: M | L10: 0
A11: CB0709 | B11: ESCAVAÇÃO MANUAL ATÉ 3,0M | C11: M3 | D11: 1 | E11: 0 | F11: I | G11: IH1901 | H11: SERVENTE (ENCARGOS INCLUSOS) | I11: H | J11: 3.5 | K11: H | L11: 0
A12: CB0735 | B12: REATERRO COMPACTADO DE VALA | C12: M3 | D12: 1 | E12: 0 | F12: I | G12: IH1901 | H12: SERVENTE (ENCARGOS INCLUSOS) | I12: H | J12: 0.65 | K12: H | L12: 0
A13: CB1301 | B13: CORTE E PREPARO DE CABEÇA DE ESTACAS | C13: UN | D13: 1 | E13: 0 | F13: I | G13: IH1601 | H13: PEDREIRO (ENCARGOS INCLUSOS) | I13: H | J13: 0.35 | K13: H | L13: 0
D14: 0 | F14: I | G14: IH1901 | H14: SERVENTE (ENCARGOS INCLUSOS) | I14: H | J14: 3.5 | K14: H | L14: 0
A15: CB2001 | B15: GEOTÊXTIL COMO FILTRO ENVOLVENDO O MATERIAL DRENANTE | C15: M2 | D15: 1 | E15: 0 | F15: I | G15: IH1901 | H15: SERVENTE (ENCARGOS INCLUSOS) | I15: H | J15: 0.03 | K15: H | L15: 0
D16: 0 | F16: I | G16: IM0901 | H16: GEOTÊXTIL | I16: M2 | J16: 1.1 | K16: M | L16: 0
A17: CB2307 | B17: CONCRETO NÃO ESTRUT. PREPARADO C/ BETONEIRA - m.o c. ndireto | C17: M3 | D17: 1 | E17: 0 | F17: I | G17: IH1901 | H17: SERVENTE (ENCARGOS INCLUSOS) | I17: H | J17: 0 | K17: H | L17: 0
D18: 0 | F18: I | G18: IM0117 | H18: AREIA IND.MÉDIA LAVADA | I18: M3 | J18: 0.778 | K18: M | L18: 0
D19: 0 | F19: I | G19: IM0305 | H19: BRITA 1 | I19: M3 | J19: 0.9658 | K19: M | L19: 0
D20: 0 | F20: I | G20: IM0406 | H20: CIMENTO PORTLAND CP-320 | I20: KG | J20: 220 | K20: M | L20: 0
A21: CB2902 | B21: GUIA PRÉ-FABRICADA DE CONCRETO | C21: M | D21: 1 | E21: 0 | F21: I | G21: IH9000 | H21: PEDREIRO (PLANEJAMENTO) | I21: H | J21: 0.3 | K21: H | L21: 0
D22: 0 | F22: I | G22: IH9001 | H22: SERVENTE (PLANEJAMENTO) | I22: H | J22: 0.3 | K22: H | L22: 0
D23: 0 | F23: I | G23: IM0903 | H23: MEIO FIO PRÉ MOLDADO DE CONCRETO (sudecap 18 MPa) C/ | I23: UN | J23: 1.3125 | K23: M | L23: 0
D24: 0 | F24: I | G24: IS9634 | H24: M.O. ASSENTAMENTO DE MEIO FIO DE RUA | I24: M | J24: 1 | K24: S | L24: 0
D25: 0 | F25: C | G25: CC1551 | H25: ARGAMASSA 1:3 (C/A) - m.o custo indireto | I25: M3 | J25: 0.01 | L25: 0
D26: 0 | F26: C | G26: CB4016 | H26: LASTRO DE CONCRETO MAGRO E= 6, 0cm - | I26: M2 | J26: 0.35 | L26: 0
D27: 0 | F27: C | G27: CB4011 | H27: APILOAMENTO MANUAL DE FUNDO DE VALAS | I27: M2 | J27: 0.35 | L27: 0
D28: 0 | F28: C | G28: CB0735 | H28: REATERRO COMPACTADO DE VALA | I28: M3 | J28: 0.25 | L28: 0
D29: 0 | F29: C | G29: CB0709 | H29: ESCAVAÇÃO MANUAL ATÉ 3,0M | I29: M3 | J29: 0.25 | L29: 0
A30: CB4011 | B30: APILOAMENTO MANUAL DE FUNDO DE VALAS | C30: M2 | D30: 1 | E30: 0 | F30: I | G30: IH1901 | H30: SERVENTE (ENCARGOS INCLUSOS) | I30: H | J30: 0.2 | K30: H | L30: 0
A31: CB4016 | B31: LASTRO DE CONCRETO MAGRO E= 6, 0cm - | C31: M2 | D31: 1 | E31: 0 | F31: I | G31: IH1601 | H31: PEDREIRO (ENCARGOS INCLUSOS) | I31: H | J31: 0.125 | K31: H | L31: 0
D32: 0 | F32: I | G32: IH1901 | H32: SERVENTE (ENCARGOS INCLUSOS) | I32: H | J32: 0.125 | K32: H | L32: 0
D33: 0 | F33: C | G33: CB2307 | H33: CONCRETO NÃO ESTRUT. PREPARADO C/ BETONEIRA - m.o c. ndireto | I33: M3 | J33: 0.06 | L33: 0
A34: CC0410 | B34: ARMAÇÃO AÇO CA-50A CORTE E DOB RA Ø < 12,5mm | C34: KG | D34: 1 | E34: 0 | F34: I | G34: IH0102 | H34: AJUDANTE DE ARMADOR (ENCARGOS INCLUSOS) | I34: H | J34: 0.07 | K34: H | L34: 0
D35: 0 | F35: I | G35: IH0108 | H35: ARMADOR (ENCARGOS INCLUSOS) | I35: H | J35: 0.07 | K35: H | L35: 0
D36: 0 | F36: I | G36: IM0110 | H36: ARAME RECOZIDO BWG 18 (antigo PG-07) | I36: KG | J36: 0.02 | K36: M | L36: 0
D37: 0 | F37: I | G37: IM0143 | H37: AÇO CA-50 / CA-60 - CORTADO E DOBRADO | I37: KG | J37: 1.02 | K37: M | L37: 0
A38: CC0636 | B38: CONCRETO ESTRUTURAL, CONTROLE TIPO B, BRITA 1 E 2, FCK = 20 | C38: M3 | D38: 1 | E38: 0 | F38: I | G38: IH1901 | H38: SERVENTE (ENCARGOS INCLUSOS) | I38: H | J38: 0 | K38: H | L38: 0
D39: 0 | F39: I | G39: IM0117 | H39: AREIA IND.MÉDIA LAVADA | I39: M3 | J39: 0.8904 | K39: M | L39: 0
D40: 0 | F40: I | G40: IM0305 | H40: BRITA 1 | I40: M3 | J40: 0.836 | K40: M | L40: 0
D41: 0 | F41: I | G41: IM0406 | H41: CIMENTO PORTLAND CP-320 | I41: KG | J41: 320 | K41: M | L41: 0
A42: CC1519 | B42: CONCRETO FCK 9.0 MPa LANÇADO EM FUNDAÇÕES | C42: M3 | D42: 1 | E42: 0 | F42: C | G42: CP2016 | H42: LANÇAMENTO CONCRETO EM FUNDA- ÇÃO | I42: M3 | J42: 1 | L42: 0
D43: 0 | F43: C | G43: CB2307 | H43: CONCRETO NÃO ESTRUT. PREPARADO C/ BETONEIRA - m.o c. ndireto | I43: M3 | J43: 1.05 | L43: 0
A44: CC1534 | B44: CONCRETO USINADO FCK 20,0 MPa LANÇADO EM FUNDAÇÕES | C44: M3 | D44: 1 | E44: 0 | F44: I | G44: IM2805 | H44: CONCRETO USINADO CONVENCIONAL FCK 20,0 MPa | I44: M3 | J44: 1.05 | K44: M | L44: 0
D45: 0 | F45: C | G45: CP2016 | H45: LANÇAMENTO CONCRETO EM FUNDA- ÇÃO | I45: M3 | J45: 1 | L45: 0
A46: CC1537 | B46: CONCRETO USINADO FCK 20,0 MPa LANÇADO EM ESTRUTURA | C46: M3 | D46: 1 | E46: 0 | F46: I | G46: IM2813 | H46: CONCRETO USIN. BOMB.FCK 20MPa | I46: M3 | J46: 1.05 | K46: M | L46: 0
D47: 0 | F47: I | G47: IS0003 | H47: BOMBEAMENTO DE CONCRETO | I47: M3 | J47: 1 | K47: S | L47: 0
D48: 0 | F48: C | G48: CP2003 | H48: LANÇAMENTO DE CONCRETO BOMBEA DO - ESTRUTURA | I48: M3 | J48: 1 | L48: 0
A49: CC1538 | B49: CONCRETO USINADO FCK 25,0 MPa LANÇADO EM ESTRUTURA | C49: M3 | D49: 1 | E49: 0 | F49: I | G49: IM2814 | H49: CONCRETO USIN. BOMB. FCK 25MPa | I49: M3 | J49: 1.05 | K49: M | L49: 0
D50: 0 | F50: I | G50: IS0003 | H50: BOMBEAMENTO DE CONCRETO | I50: M3 | J50: 1 | K50: S | L50: 0
D51: 0 | F51: C | G51: CP2003 | H51: LANÇAMENTO DE CONCRETO BOMBEA DO - ESTRUTURA | I51: M3 | J51: 1 | L51: 0
A52: CC1539 | B52: CONCRETO USINADO FCK 30,0 MPa LANÇADO EM ESTRUTURA | C52: M3 | D52: 1 | E52: 0 | F52: I | G52: IM2815 | H52: CONCRETO USIN. BOMB.FCK 30MPa | I52: M3 | J52: 1.05 | K52: M | L52: 0
D53: 0 | F53: I | G53: IS0003 | H53: BOMBEAMENTO DE CONCRETO | I53: M3 | J53: 1 | K53: S | L53: 0
D54: 0 | F54: C | G54: CP2003 | H54: LANÇAMENTO DE CONCRETO BOMBEA DO - ESTRUTURA | I54: M3 | J54: 1 | L54: 0
A55: CC1540 | B55: CONCRETO USINADO FCK 35,0 MPa LANÇADO EM ESTRUTURA | C55: M3 | D55: 1 | E55: 0 | F55: I | G55: IM2817 | H55: CONCRETO USIN. BOMB. FCK 35MPa | I55: M3 | J55: 1.05 | K55: M | L55: 0
D56: 0 | F56: I | G56: IS0003 | H56: BOMBEAMENTO DE CONCRETO | I56: M3 | J56: 1 | K56: S | L56: 0
D57: 0 | F57: C | G57: CP2003 | H57: LANÇAMENTO DE CONCRETO BOMBEA DO - ESTRUTURA | I57: M3 | J57: 1 | L57: 0
A58: CC1541 | B58: CONCRETO USINADO FCK 40,0 MPa LANÇADO EM ESTRUTURA | C58: M3 | D58: 1 | E58: 0 | F58: I | G58: IM2816 | H58: CONCRETO USIN. BOMB. FCK 40MPa | I58: M3 | J58: 1.05 | K58: M | L58: 0
D59: 0 | F59: I | G59: IS0003 | H59: BOMBEAMENTO DE CONCRETO | I59: M3 | J59: 1 | K59: S | L59: 0
D60: 0 | F60: C | G60: CP2003 | H60: LANÇAMENTO DE CONCRETO BOMBEA DO - ESTRUTURA | I60: M3 | J60: 1 | L60: 0
A61: CC1551 | B61: ARGAMASSA 1:3 (C/A) - m.o custo indireto | C61: M3 | D61: 1 | E61: 0 | F61: I | G61: IH1901 | H61: SERVENTE (ENCARGOS INCLUSOS) | I61: H | J61: 0 | K61: H | L61: 0
D62: 0 | F62: I | G62: IM0117 | H62: AREIA IND.MÉDIA LAVADA | I62: M3 | J62: 1.216 | K62: M | L62: 0
D63: 0 | F63: I | G63: IM0406 | H63: CIMENTO PORTLAND CP-320 | I63: KG | J63: 486 | K63: M | L63: 0
A64: CC1552 | B64: ARGAMASSA 1:4 (C/A) PENEIRADA m.o custo indireto | C64: M3 | D64: 1 | E64: 0 | F64: I | G64: IH1901 | H64: SERVENTE (ENCARGOS INCLUSOS) | I64: H | J64: 0 | K64: H | L64: 0
D65: 0 | F65: I | G65: IM0117 | H65: AREIA IND.MÉDIA LAVADA | I65: M3 | J65: 0.935 | K65: M | L65: 0
D66: 0 | F66: I | G66: IM0406 | H66: CIMENTO PORTLAND CP-320 | I66: KG | J66: 365 | K66: M | L66: 0
A67: CC1554 | B67: ARGAMASSA 1:6 (C/A) PENEIRADA M.O CUSTO INDIRETO | C67: M3 | D67: 1 | E67: 0 | F67: I | G67: IH1901 | H67: SERVENTE (ENCARGOS INCLUSOS) | I67: H | J67: 0 | K67: H | L67: 0
D68: 0 | F68: I | G68: IM0117 | H68: AREIA IND.MÉDIA LAVADA | I68: M3 | J68: 0.935 | K68: M | L68: 0
D69: 0 | F69: I | G69: IM0406 | H69: CIMENTO PORTLAND CP-320 | I69: KG | J69: 243 | K69: M | L69: 0
A70: CC1558 | B70: ARGAMASSA 1:2:8 (C:C:A) m.o custo indireto | C70: M3 | D70: 1 | E70: 0 | F70: I | G70: IH1901 | H70: SERVENTE (ENCARGOS INCLUSOS) | I70: H | J70: 0 | K70: H | L70: 0
D71: 0 | F71: I | G71: IM0117 | H71: AREIA IND.MÉDIA LAVADA | I71: M3 | J71: 1.216 | K71: M | L71: 0
D72: 0 | F72: I | G72: IM0406 | H72: CIMENTO PORTLAND CP-320 | I72: KG | J72: 182 | K72: M | L72: 0
D73: 0 | F73: I | G73: IM0410 | H73: CAL HIDRATADA CHI | I73: KG | J73: 182 | K73: M | L73: 0
A74: CC1559 | B74: CONCRETO USINADO BOMBEADO FCK 20,0 MPa ESPECIAL ESTACAS | C74: M3 | D74: 1 | E74: 0 | F74: I | G74: IS0003 | H74: BOMBEAMENTO DE CONCRETO | I74: M3 | J74: 1.25 | K74: S | L74: 0
D75: 0 | F75: I | G75: IM3590 | H75: CONCRETO ESPECIAL P/ESTACA HE LICE FCK20MPa - SLUMP 20±2cm | I75: M3 | J75: 1.25 | K75: M | L75: 0
A76: CC1572 | B76: ALVENARIA DE BLOCO CHEIO E= 15cm | C76: M2 | D76: 1 | E76: 0 | F76: I | G76: IH1601 | H76: PEDREIRO (ENCARGOS INCLUSOS) | I76: H | J76: 1.375 | K76: H | L76: 0
D77: 0 | F77: I | G77: IH1901 | H77: SERVENTE (ENCARGOS INCLUSOS) | I77: H | J77: 1.1 | K77: H | L77: 0
D78: 0 | F78: I | G78: IM2827 | H78: BLOCO DE CONCRETO 14X19X39cm - VEDAÇÃO | I78: UN | J78: 13.4 | K78: M | L78: 0
D79: 0 | F79: C | G79: CC1558 | H79: ARGAMASSA 1:2:8 (C:C:A) m.o custo indireto | I79: M3 | J79: 0.015 | L79: 0
D80: 0 | F80: C | G80: CZ9601 | H80: CONCRETO ESTRUTURAL FCK20,0MPa LANÇADO EM FUNDAÇÃO | I80: M3 | J80: 0.098 | L80: 0
D81: 0 | F81: C | G81: CP2002 | H81: ARMAÇÃO AÇO CA-50A CORTE E DO BRA ø <12,5MM | I81: KG | J81: 5.775 | L81: 0
A82: CC1573 | B82: ALVENARIA DE BLOCO CHEIO E= 20cm | C82: M2 | D82: 1 | E82: 0 | F82: I | G82: IH1601 | H82: PEDREIRO (ENCARGOS INCLUSOS) | I82: H | J82: 1.75 | K82: H | L82: 0
D83: 0 | F83: I | G83: IH1901 | H83: SERVENTE (ENCARGOS INCLUSOS) | I83: H | J83: 1.4 | K83: H | L83: 0
D84: 0 | F84: I | G84: IM2828 | H84: BLOCO DE CONCRETO 19X19X39cm - VEDAÇÃO | I84: UN | J84: 13.4 | K84: M | L84: 0
D85: 0 | F85: C | G85: CC1558 | H85: ARGAMASSA 1:2:8 (C:C:A) m.o custo indireto | I85: M3 | J85: 0.02 | L85: 0
D86: 0 | F86: C | G86: CZ9601 | H86: CONCRETO ESTRUTURAL FCK20,0MPa LANÇADO EM FUNDAÇÃO | I86: M3 | J86: 0.13 | L86: 0
D87: 0 | F87: C | G87: CP2002 | H87: ARMAÇÃO AÇO CA-50A CORTE E DO BRA ø <12,5MM | I87: KG | J87: 5.775 | L87: 0
A88: CC1593 | B88: PISO CIMENTADO LISO E= 3,0CM | C88: M2 | D88: 1 | E88: 0 | F88: I | G88: IH9000 | H88: PEDREIRO (PLANEJAMENTO) | I88: H | J88: 0.4 | K88: H | L88: 0
D89: 0 | F89: I | G89: IH9001 | H89: SERVENTE (PLANEJAMENTO) | I89: H | J89: 0.2 | K89: H | L89: 0
D90: 0 | F90: I | G90: IM0406 | H90: CIMENTO PORTLAND CP-320 | I90: KG | J90: 1 | K90: M | L90: 0
D91: 0 | F91: I | G91: IM4553 | H91: ARGAMASSA PRONTA - CONTRAPISO | I91: KG | J91: 70 | K91: M | L91: 0
D92: 0 | F92: I | G92: IS0215 | H92: M.O. PISO CIMENTADO 3CM | I92: M2 | J92: 1 | K92: S | L92: 0
A93: CC1618 | B93: LIMPEZA DO TERRENO | C93: M2 | D93: 1 | E93: 0 | F93: I | G93: IH1901 | H93: SERVENTE (ENCARGOS INCLUSOS) | I93: H | J93: 0.3 | K93: H | L93: 0
A94: CC1625 | B94: CORRIMÃO EM TUBO DE FERRO | C94: M | D94: 1 | E94: 0 | F94: I | G94: IM2890 | H94: CORRIMÃO EM TUBO DE FERRO ø1 1/4” PADRÃO CORPO DE BOMBEIRO | I94: M | J94: 1 | K94: M | L94: 0
D95: 0 | F95: C | G95: CX1506 | H95: ASSENTAMENTO DE ESQUADRIAS | I95: M2 | J95: 0.5 | L95: 0
A96: CC1632 | B96: TERRA VEGETAL EM JARDINS | C96: M2 | D96: 1 | E96: 0 | F96: I | G96: IH1901 | H96: SERVENTE (ENCARGOS INCLUSOS) | I96: H | J96: 0.6 | K96: H | L96: 0
D97: 0 | F97: I | G97: IM2230 | H97: TERRA VEGETAL | I97: M3 | J97: 0.105 | K97: M | L97: 0
A98: CC1649 | B98: ALÇAPÃO METÁLICO 80x80 | C98: UN | D98: 1 | E98: 0 | F98: I | G98: IM4651 | H98: ALÇAPÃO METÁLICO 70x70 CM | I98: UN | J98: 1 | K98: M | L98: 0
D99: 0 | F99: C | G99: CS1581 | H99: ASSENTAMENTO DE ESQUADRIAS | I99: M2 | J99: 0.49 | L99: 0
A100: CC1650 | B100: BRISES METÁLICOS | C100: M2 | D100: 1 | E100: 0 | F100: I | G100: IM3101 | H100: BRISE METÁLICO | I100: M2 | J100: 1 | K100: M | L100: 0
D101: 0 | F101: C | G101: CX1506 | H101: ASSENTAMENTO DE ESQUADRIAS | I101: M2 | J101: 1 | L101: 0
...

Sheet import_CPU
A1: MODELO DE IMPORTAÇÃO DE COMPOSIÇÕES
A3: CÓD | B3: DESCRIÇÃO | C3: UND | D3: Prod. Equipe | E3: origem | F3: tipo | G3: INSUMO | H3: DESCRIÇÃO IS | I3: UND | J3: ÍNDICE | K3: Grupo | L3: origem
A5: CZ7030 | B5: PISO EM PORCELANATO À DEFINIR - GOURMET | C5: M2 | D5: 1 | E5: 0 | F5: C | G5: CP2202 | H5: REJUNTE PORCELANATO | I5: M2 | J5: 1 | K5: C | L5: 0
A6: CZ7030 | B6: PISO EM PORCELANATO À DEFINIR - GOURMET | C6: M2 | D6: 1 | E6: 0 | F6: I | G6: IH9000 | H6: PEDREIRO (PLANEJAMENTO) | I6: H | J6: 0.88 | K6: H | L6: 0
A7: CZ7030 | B7: PISO EM PORCELANATO À DEFINIR - GOURMET | C7: M2 | D7: 1 | E7: 0 | F7: I | G7: IH9001 | H7: SERVENTE (PLANEJAMENTO) | I7: H | J7: 0.44 | K7: H | L7: 0
A8: CZ7030 | B8: PISO EM PORCELANATO À DEFINIR - GOURMET | C8: M2 | D8: 1 | E8: 0 | F8: I | G8: IM2844 | H8: ARGAMASSA AC-3 | I8: KG | J8: 8 | K8: M | L8: 0
A9: CZ7030 | B9: PISO EM PORCELANATO À DEFINIR - GOURMET | C9: M2 | D9: 1 | E9: 0 | F9: I | G9: =CONCATENATE("IM",MID(A9,3,6)) -> IM7030 | H9: =B9 -> PISO EM PORCELANATO À DEFINIR - GOURMET | I9: =C9 -> M2 | J9: 1.05 | K9: M | L9: 0
A10: CZ7030 | B10: PISO EM PORCELANATO À DEFINIR - GOURMET | C10: M2 | D10: 1 | E10: 0 | F10: I | G10: IS0342 | H10: M.O. PISO PORCELANATO | I10: M2 | J10: 1 | K10: S | L10: 0
B21: MODELO DE IMPORTAÇÃO DE COMPOSIÇÃO

Sheet import_IS
A1: MODELO DE IMPORTAÇÃO DE INSUMOS COM PREÇO
A3: CÓD | B3: DESCRIÇÃO COMP. | C3: DESCRIÇÃO ABREV, | D3: UND | E3: PREÇO | F3: GRUPO IS | G3: ORIGEM
A5: IM2819 | B5: TIJOLO CERÂMICO FURADO 09X19X29 CM | C5: TIJOLO CERÂMICO FURADO 09X19X29 CM | D5: UN | E5: 0 | F5: M | G5: 0
A6: IS5024 | B6: EMPREITEIRO PARA ASSENTAMENTO DA 1º FIADA PREENCHIDA COM | C6: EMPREITEIRO PARA ASSENTAMENTO DA 1º FIADA PREENCHIDA COM | D6: M | E6: 0 | F6: S | G6: 0
A7: IM1984 | B7: ADITIVO INCORPORADOR DE AR - REF.: CEMIX AIR | C7: ADITIVO INCORPORADOR DE AR - REF.: CEMIX AIR | D7: L | E7: 0 | F7: M | G7: 0
A8: IM0165 | B8: ARGAMASSA PRONTA MULTIUSO | C8: ARGAMASSA PRONTA MULTIUSO | D8: KG | E8: 0 | F8: M | G8: 0
A9: IM1985 | B9: TIJOLO CERÂMICO FURADO 14X19X29CM - ACÚSTICO | C9: TIJOLO CERÂMICO FURADO 14X19X29CM - ACÚSTICO | D9: UN | E9: 0 | F9: M | G9: 0
A10: IS0032 | B10: M.O. ALVENARIA TIJOLO CERÂMICO 14 CM | C10: M.O. ALVENARIA TIJOLO CERÂMICO 14 CM | D10: M2 | E10: 0 | F10: S | G10: 0
B18: MODELO DE IMPORTAÇÃO DE INSUMOS

Sheet import_Plan
A1: MODELO DE IMPORTAÇÃO DE PLANILHA
A2: ITEM | B2: CÓD CPU | C2: DESCRIÇÃO | D2: UND | E2: QTDE | F2: ORIGEM
A4: 1 | C4: TAXA DE ADMINISTRAÇÃO | F4: 0
A5: 01.01 | B5: CX1701 | C5: TAXA DE ADMINISTRAÇÃO - 13% (CUSTOS DIRETOS + INDIRETOS + PROJETOS) | D5: VB | E5: 1 | F5: 0
F6: 0
A7: 2 | C7: PROJETOS / SERVIÇOS TÉCNICOS | F7: 0
A8: 02.01 | B8: CX1720 | C8: PROJETO TOPOGRÁFICO - Custo informado pelo cliente | D8: VB | E8: 1 | F8: 0
A9: 02.02 | B9: CX1728 | C9: SONDAGEM - Custo informado pelo cliente | D9: VB | E9: 1 | F9: 0
A10: 02.03 | B10: CX1705 | C10: PROJETO ELÉTRICO DO CANTEIRO - Custo informado pelo cliente | D10: VB | E10: 1 | F10: 0
A11: 02.04 | B11: CX1702 | C11: PROJETO ARQUITETÔNICO - Custo informado pelo cliente | D11: VB | E11: 1 | F11: 0
A12: 02.05 | B12: CX1724 | C12: PROJETO EXECUTIVO - Custo informado pelo cliente | D12: VB | E12: 1 | F12: 0
A13: 02.06 | B13: CX1704 | C13: PROJETO DE INSTALAÇÕES COMPLEMENTARES | D13: VB | E13: 1 | F13: 0
A14: 02.07 | B14: CX1707 | C14: PROJETO DE PREVENÇÃO E COMBATE A INCÊNDIO - Custo informado pelo cliente | D14: VB | E14: 1 | F14: 0
A15: 02.08 | B15: CX1711 | C15: PROJETO ESTRUTURAL - Custo informado pelo cliente | D15: VB | E15: 1 | F15: 0
A16: 02.09 | B16: CX1713 | C16: PROJETO FUNDAÇÃO - Custo informado pelo cliente | D16: VB | E16: 1 | F16: 0
A17: 02.10 | B17: CX1725 | C17: PROJETO DE TERRAPLENAGEM - Custo informado pelo cliente | D17: VB | E17: 1 | F17: 0
A18: 02.11 | B18: CX1719 | C18: PROJETO PAISAGISMO - Custo informado pelo cliente | D18: VB | E18: 1 | F18: 0
A19: 02.12 | B19: CX1723 | C19: PROJETO DE DRENAGEM | D19: VB | E19: 1 | F19: 0
C26: MODELO DE IMPORTAÇÃO DE PLANILHA
